cpu/src/alu.v
module alu(
    input [3:0] i_alu_op,
    input [31:0] i_a,          // input a
    input [31:0] i_b,          // input b
    output reg [31:0] o_result,    //ouput result
    output o_zero
); 
    assign o_zero = (o_result == 32'b0);
    
    always @(*) begin
        case(i_alu_op)
            4'b0000 : o_result = i_a + i_b;       // ADD
            4'b0001 : o_result = i_a - i_b;       // SUB
            4'b0010 : o_result = i_a ^ i_b;       // XOR
            4'b0011 : o_result = i_a | i_b;       // OR
            4'b0100 : o_result = i_a & i_b;       // AND
            4'b0101 : o_result = i_a << i_b;      // SLL
            4'b0110 : o_result = i_a >> i_b;      // SRL
            4'b0111 : o_result = i_a >>> i_b;     // SRA
            4'b1000 : o_result = {31'b0, ($signed(i_a) < $signed(i_b))};   // SLT
            4'b1001 : o_result = {31'b0, (i_a < i_b)};                      // SLTU
        default : o_result = 32'b0;
        endcase
    end
endmodule

cpu/src/imm_gen.v
module imm_gen(
    input [31:0] i_instr,
    input [1:0] i_instr_type,
    output reg [31:0] o_imm
); 
    parameter I_TYPE = 2'b01; 
    parameter B_TYPE = 2'b10;
    parameter S_TYPE = 2'b11;

    always @(*) begin
        case (i_instr_type)
            I_TYPE : o_imm = { {16{i_instr[31]}}, i_instr[31:16] };
            B_TYPE : o_imm = { {15{i_instr[31]}}, i_instr[31:20], i_instr[11:8], 1'b0 };
            S_TYPE : o_imm = { {16{i_instr[31]}}, i_instr[31:20], i_instr[11:8]};
            default : o_imm = 32'b0;
        endcase
    end
endmodule

cpu/src/alu_control_unit.v
module alu_control_unit(
    input [5:0] i_opcode,
    input [1:0] i_funct2, // unused currently
    output reg [3:0] o_alu_op
);
    parameter R_TYPE = 2'b00;
    parameter I_TYPE = 2'b01; 
    parameter B_TYPE = 2'b10;
    parameter S_TYPE = 2'b11;
    parameter ADD_OP = 4'b0000;
    parameter SUB_OP = 4'b0001;     

    always @(*) begin
        case (i_opcode[5:4])                        // instruction type
            R_TYPE  :  o_alu_op = i_opcode[3:0]; // opcode already IS the ALU op
            I_TYPE  :  begin
                if (i_opcode[3:0] == 4'b1111)
                    o_alu_op = ADD_OP;  // LW: address = rs1 + imm
                else
                    o_alu_op = i_opcode[3:0];  // ordinary ALU-immediate op
                end
            S_TYPE  :  o_alu_op = ADD_OP;     // address calc, opcode bits aren't an ALU op here
            B_TYPE  :  o_alu_op = SUB_OP;     // if using ALU for comparison
            default :  o_alu_op = ADD_OP;
        endcase
    end 
endmodule

cpu/src/reg_file.v
module reg_file(
    input i_clk,
    input i_we,
    input i_rst,
    input [3:0] i_rd_addr,  // write destination
    input [31:0] i_rd_data, // write data
    input [3:0] i_rs1_addr, // port 1
    input [3:0] i_rs2_addr, // port 2
    output [31:0] o_rs1_data,
    output [31:0] o_rs2_data
);
    reg [31:0] regs[15:0]; // 16 - 32 bit general purpose registers
    // synchronous write
    always @(posedge i_clk) begin
        if (i_we && (i_rd_addr != 4'b0)) 
            regs[i_rd_addr] <= i_rd_data; 
    end

    // combinational read
    assign o_rs1_data = (i_rs1_addr == 4'b0) ? 32'b0 : regs[i_rs1_addr];
    assign o_rs2_data = (i_rs2_addr == 4'b0) ? 32'b0 : regs[i_rs2_addr];
endmodule

cpu/src/control_unit.v
`default_nettype none
module control_unit (
    input [5:0] i_opcode,
    output reg o_reg_write,   // write result into rd? 1 for R-type, I-type, Loads, 0 for S-Type, B-Type
    output reg o_alu_src,     // 1 for I-Type, S-Type (any immediates), 0 for R-Type, B-Type
    output reg o_mem_write,   // write to data memory? 1 for S-Type ONLY opcode[5:4] = 2'b11
    output reg o_mem_read,    // read from data memory? 1 for Loads ONLY (opcode[3:0] = 4'b1111)
    output reg o_mem_to_reg,  // write to rd from memory or from registers? 1 = memory (LW), 0 = everything else
    output reg o_branch       // is this a conditional branch? 1 for B-Type only
); 
    parameter R_TYPE = 2'b00;
    parameter I_TYPE = 2'b01; 
    parameter B_TYPE = 2'b10;
    parameter S_TYPE = 2'b11;

    always @(*) begin
        case (i_opcode[5:4])
            R_TYPE : begin
                o_reg_write = 1'b1; o_alu_src = 1'b0;
                o_mem_write = 1'b0; o_mem_read = 1'b0;
                o_mem_to_reg = 1'b0; o_branch = 1'b0;
            end

            I_TYPE : begin
                o_reg_write = 1'b1; o_alu_src = 1'b1; o_mem_write = 1'b0; o_branch = 1'b0;  
                if (i_opcode[3:0] == 4'b1111) begin // LW instruction
                    o_mem_to_reg = 1'b1; o_mem_read = 1'b1;
                end else begin 
                    o_mem_to_reg = 1'b0; o_mem_read = 1'b0;
                end
            end

            B_TYPE : begin
                o_reg_write = 1'b0; o_alu_src = 1'b0;
                o_mem_write = 1'b0; o_mem_read = 1'b0;
                o_mem_to_reg = 1'b0; o_branch = 1'b1;
            end

            S_TYPE : begin
                o_reg_write = 1'b0; o_alu_src = 1'b1;
                o_mem_write = 1'b1; o_mem_read = 1'b0;
                o_mem_to_reg = 1'b0; o_branch = 1'b0;
            end

            default : begin
                o_reg_write = 1'b0; o_alu_src = 1'b0;
                o_mem_write = 1'b0; o_mem_read = 1'b0;
                o_mem_to_reg = 1'b0; o_branch = 1'b0;
            end
        endcase     
    end
endmodule

cpu/src/instr_mem.v
module instr_mem(
    input [31:0] i_pc,
    output [31:0]  o_instr
); 
    reg  [31:0] instr_mem [0:255];

    // byte indexed --> pc increments by 4 (since instr = 32 bits)
    // pc: 0x0 0x4 0x8 0xC 0x10
    // slicing from 31:2 is equal to >> 2; (divide by 4)
    // 0x0 >> 2 = 0, 0x4 >> 2 = 1, 0x8 >> 2 = 2, ..
    // aligned w/mem[0], mem[1], mem[2], mem[...]
    assign o_instr = instr_mem[i_pc[31:2]];

endmodule

cpu/src/pc.v
module pc(
    input i_clk,
    input i_rst,
    input [31:0] i_pc_next,
    output reg [31:0] o_pc_out
); 
    always @(posedge i_clk) begin
        if (i_rst) 
            o_pc_out <= 32'b0;
        else
            o_pc_out <= i_pc_next;
    end
endmodule

cpu/src/cpu.v
module cpu(
    input clk,
    input rst,

    // incoming memory response
    input  [31:0] mem_read_data,

    // outgoing memory request
    output [31:0] mem_addr,
    output [31:0] mem_write_data,
    output        mem_read,
    output        mem_write
    
);  
    
    wire [31:0] pc_current;
    wire [31:0] branch_target = pc_current + (imm_out << 1); //only shift 1, since B-Type has implicit 0;

    wire branch_condition_met = (instr[7:6] /*funct2*/ == 2'b00) ? zero_flag : ~zero_flag;
    wire branch_taken = branch & branch_condition_met;
    
    wire[31:0] pc_next = branch_taken ? branch_target : pc_current + 4;

    pc u_pc(.i_clk(clk), .i_rst(rst), .i_pc_next(pc_next), 
            .o_pc_out(pc_current));

    wire [31:0] instr;

    instr_mem u_instr_mem(.i_pc(pc_current), 
                          .o_instr(instr));

    wire reg_write, alu_src, mem_write_internal, mem_read_internal, mem_to_reg, branch; //mem write and read are internal signals fr CPU sent to data memory OUTSIDE

    control_unit u_control_unit(.i_opcode(instr[5:0]), 
                                .o_reg_write(reg_write), .o_alu_src(alu_src), .o_mem_write(mem_write_internal), 
                                .o_mem_read(mem_read_internal), .o_mem_to_reg(mem_to_reg), .o_branch(branch));

    wire [31:0] rs1_out, rs2_out;
    wire [31:0] rd_in  = mem_to_reg ? mem_read_data : alu_out;

    reg_file u_reg_file(.i_clk(clk), .i_we(reg_write), .i_rst(rst), 
                        .i_rd_addr(instr[11:8]), .i_rd_data(rd_in), .i_rs1_addr(instr[15:12]), .i_rs2_addr(instr[19:16]), 
                        .o_rs1_data(rs1_out), .o_rs2_data(rs2_out));
    
    wire [3:0] alu_op;

    alu_control_unit u_alu_control_unit(.i_opcode(instr[5:0]), .i_funct2(instr[7:6]), 
                                        .o_alu_op(alu_op));

    wire [31:0] imm_out;

    imm_gen u_imm_gen(.i_instr(instr), .i_instr_type(instr[5:4]), 
                      .o_imm(imm_out));

    wire zero_flag;

    wire [31:0] alu_a = rs1_out;
    wire [31:0] alu_b = alu_src ? imm_out : rs2_out;
    wire [31:0] alu_out;

    alu u_alu(.i_alu_op(alu_op), .i_a(alu_a), .i_b(alu_b), 
              .o_result(alu_out), .o_zero(zero_flag));

    assign mem_addr = alu_out;
    assign mem_write_data = rs2_out;
    assign mem_read = mem_read_internal;
    assign mem_write = mem_write_internal;

endmodule

cpu/testbenches/alu_path_cpu_tb.v
`timescale 1ns/1ps

module alu_path_cpu_tb;

    reg clk = 0;
    reg rst;

    wire [31:0] mem_addr, mem_write_data;
    wire        mem_read, mem_write;
    reg  [31:0] mem_read_data = 32'b0; // no real data_mem for this ALU-only test

    cpu UUT (
        .clk           (clk),
        .rst           (rst),
        .mem_read_data (mem_read_data),
        .mem_addr      (mem_addr),
        .mem_write_data(mem_write_data),
        .mem_read      (mem_read),
        .mem_write     (mem_write)
    );

    always #5 clk = ~clk;

    initial begin
        $dumpfile("alu_path_cpu_tb.vcd");
        $dumpvars(0, alu_path_cpu_tb);
        $monitor("t=%0t | pc=%0d instr=%h | rd_in=%0d rs1=%0d rs2=%0d imm=%0d | alu_a=%0d alu_b=%0d alu_op=%b alu_out=%0d zero=%b | reg_write=%b mem_to_reg=%b branch=%b branch_taken=%b",
                  $time,
                  UUT.pc_current, UUT.instr,
                  UUT.rd_in, UUT.rs1_out, UUT.rs2_out, UUT.imm_out,
                  UUT.alu_a, UUT.alu_b, UUT.alu_op, UUT.alu_out, UUT.zero_flag,
                  UUT.reg_write, UUT.mem_to_reg, UUT.branch, UUT.branch_taken);
        
        // Preload a tiny test program directly into instruction memory.
        // Field layout: {imm/top16[31:16], rs1[15:12], rd[11:8], funct2[7:6], opcode[5:0]}
        // opcode[5:0] = {type[1:0], alu_op[3:0]}

        // ADDI x1, x0, 5      -> I_TYPE(01), ADD(0000), rd=1, rs1=0, imm=5
        UUT.u_instr_mem.instr_mem[0] = {16'd5,  4'h0, 4'h1, 2'b00, 6'b01_0000};

        // ADDI x2, x0, 10     -> I_TYPE(01), ADD(0000), rd=2, rs1=0, imm=10
        UUT.u_instr_mem.instr_mem[1] = {16'd10, 4'h0, 4'h2, 2'b00, 6'b01_0000};

        // ADD x3, x1, x2      -> R_TYPE(00), ADD(0000), rd=3, rs1=1, rs2=2
        UUT.u_instr_mem.instr_mem[2] = {12'b0, 4'h2, 4'h1, 4'h3, 2'b00, 6'b00_0000};

        rst = 1;
        @(negedge clk);
        rst = 0;

        // let the three instructions execute
        repeat (6) @(posedge clk);

        $display("x1 = %0d (expect 5)",  UUT.u_reg_file.regs[1]);
        $display("x2 = %0d (expect 10)", UUT.u_reg_file.regs[2]);
        $display("x3 = %0d (expect 15)", UUT.u_reg_file.regs[3]);

        if (UUT.u_reg_file.regs[3] == 32'd15)
            $display("Test Passed");
        else
            $display("Test Failed");

        $finish;
    end

endmodule

/*
`timescale 1ns/1ps

module cpu_tb;

    reg clk = 0;
    reg rst;

    wire [31:0] mem_addr, mem_write_data;
    wire        mem_read, mem_write;
    reg  [31:0] mem_read_data = 32'b0; // no real data_mem for this ALU-only test

    cpu UUT (
        .clk           (clk),
        .rst           (rst),
        .mem_read_data (mem_read_data),
        .mem_addr      (mem_addr),
        .mem_write_data(mem_write_data),
        .mem_read      (mem_read),
        .mem_write     (mem_write)
    );

    always #5 clk = ~clk;

    initial begin
        $dumpfile("cpu_tb.vcd");
        $dumpvars(0, cpu_tb);

        $monitor("t=%0t | pc=%0d instr=%h | rd_in=%0d rs1=%0d rs2=%0d imm=%0d | alu_a=%0d alu_b=%0d alu_op=%b alu_out=%0d zero=%b | reg_write=%b mem_to_reg=%b branch=%b branch_taken=%b",
                  $time,
                  UUT.pc_current, UUT.instr,
                  UUT.rd_in, UUT.rs1_out, UUT.rs2_out, UUT.imm_out,
                  UUT.alu_a, UUT.alu_b, UUT.alu_op, UUT.alu_out, UUT.zero_flag,
                  UUT.reg_write, UUT.mem_to_reg, UUT.branch, UUT.branch_taken);

        // Preload a tiny test program directly into instruction memory.
        // Field layout: {imm/top16[31:16], rs1[15:12], rd[11:8], funct2[7:6], opcode[5:0]}
        // opcode[5:0] = {type[1:0], alu_op[3:0]}

        // ADDI x1, x0, 5      -> I_TYPE(01), ADD(0000), rd=1, rs1=0, imm=5
        UUT.u_instr_mem.instr_mem[0] = {16'd5,  4'h0, 4'h1, 2'b00, 6'b01_0000};

        // ADDI x2, x0, 10     -> I_TYPE(01), ADD(0000), rd=2, rs1=0, imm=10
        UUT.u_instr_mem.instr_mem[1] = {16'd10, 4'h0, 4'h2, 2'b00, 6'b01_0000};

        // ADD x3, x1, x2      -> R_TYPE(00), ADD(0000), rd=3, rs1=1, rs2=2
        UUT.u_instr_mem.instr_mem[2] = {12'b0, 4'h2, 4'h1, 4'h3, 2'b00, 6'b00_0000};

        // Drive rst on negedge, not immediately after posedge, to avoid
        // racing pc.v's own posedge-triggered reset logic at the same instant.
        rst = 1;
        @(negedge clk);
        rst = 0;
        @(posedge clk);

        // let the three instructions execute
        repeat (6) @(posedge clk);

        $display("x1 = %0d (expect 5)",  UUT.u_reg_file.regs[1]);
        $display("x2 = %0d (expect 10)", UUT.u_reg_file.regs[2]);
        $display("x3 = %0d (expect 15)", UUT.u_reg_file.regs[3]);

        if (UUT.u_reg_file.regs[3] == 32'd15)
            $display("Test Passed");
        else
            $display("Test Failed");

        $finish;
    end

endmodule
*/

cpu/sim/alu_path_cpu_tb.vcd
$date
	Sat Aug 29 17:49:01 2026
$end
$version
	Icarus Verilog
$end
$timescale
	1ps
$end
$scope module alu_path_cpu_tb $end
$var wire 32 ! mem_write_data [31:0] $end
$var wire 1 " mem_write $end
$var wire 1 # mem_read $end
$var wire 32 $ mem_addr [31:0] $end
$var reg 1 % clk $end
$var reg 32 & mem_read_data [31:0] $end
$var reg 1 ' rst $end
$scope module UUT $end
$var wire 32 ( alu_a [31:0] $end
$var wire 1 ) branch_taken $end
$var wire 1 % clk $end
$var wire 32 * mem_addr [31:0] $end
$var wire 1 # mem_read $end
$var wire 32 + mem_read_data [31:0] $end
$var wire 1 " mem_write $end
$var wire 32 , mem_write_data [31:0] $end
$var wire 1 ' rst $end
$var wire 1 - zero_flag $end
$var wire 32 . rs2_out [31:0] $end
$var wire 32 / rs1_out [31:0] $end
$var wire 1 0 reg_write $end
$var wire 32 1 rd_in [31:0] $end
$var wire 32 2 pc_next [31:0] $end
$var wire 32 3 pc_current [31:0] $end
$var wire 1 4 mem_write_internal $end
$var wire 1 5 mem_to_reg $end
$var wire 1 6 mem_read_internal $end
$var wire 32 7 instr [31:0] $end
$var wire 32 8 imm_out [31:0] $end
$var wire 32 9 branch_target [31:0] $end
$var wire 1 : branch_condition_met $end
$var wire 1 ; branch $end
$var wire 1 < alu_src $end
$var wire 32 = alu_out [31:0] $end
$var wire 4 > alu_op [3:0] $end
$var wire 32 ? alu_b [31:0] $end
$scope module u_alu $end
$var wire 32 @ i_a [31:0] $end
$var wire 32 A i_b [31:0] $end
$var wire 1 - o_zero $end
$var wire 4 B i_alu_op [3:0] $end
$var reg 32 C o_result [31:0] $end
$upscope $end
$scope module u_alu_control_unit $end
$var wire 2 D i_funct2 [1:0] $end
$var wire 6 E i_opcode [5:0] $end
$var parameter 4 F ADD_OP $end
$var parameter 2 G B_TYPE $end
$var parameter 2 H I_TYPE $end
$var parameter 2 I R_TYPE $end
$var parameter 4 J SUB_OP $end
$var parameter 2 K S_TYPE $end
$var reg 4 L o_alu_op [3:0] $end
$upscope $end
$scope module u_control_unit $end
$var wire 6 M i_opcode [5:0] $end
$var parameter 2 N B_TYPE $end
$var parameter 2 O I_TYPE $end
$var parameter 2 P R_TYPE $end
$var parameter 2 Q S_TYPE $end
$var reg 1 < o_alu_src $end
$var reg 1 ; o_branch $end
$var reg 1 6 o_mem_read $end
$var reg 1 5 o_mem_to_reg $end
$var reg 1 4 o_mem_write $end
$var reg 1 0 o_reg_write $end
$upscope $end
$scope module u_imm_gen $end
$var wire 2 R i_instr_type [1:0] $end
$var wire 32 S i_instr [31:0] $end
$var parameter 2 T B_TYPE $end
$var parameter 2 U I_TYPE $end
$var parameter 2 V S_TYPE $end
$var reg 32 W o_imm [31:0] $end
$upscope $end
$scope module u_instr_mem $end
$var wire 32 X o_instr [31:0] $end
$var wire 32 Y i_pc [31:0] $end
$upscope $end
$scope module u_pc $end
$var wire 1 % i_clk $end
$var wire 32 Z i_pc_next [31:0] $end
$var wire 1 ' i_rst $end
$var reg 32 [ o_pc_out [31:0] $end
$upscope $end
$scope module u_reg_file $end
$var wire 1 % i_clk $end
$var wire 4 \ i_rd_addr [3:0] $end
$var wire 32 ] i_rd_data [31:0] $end
$var wire 4 ^ i_rs1_addr [3:0] $end
$var wire 4 _ i_rs2_addr [3:0] $end
$var wire 1 ' i_rst $end
$var wire 1 0 i_we $end
$var wire 32 ` o_rs2_data [31:0] $end
$var wire 32 a o_rs1_data [31:0] $end
$upscope $end
$upscope $end
$upscope $end
$enddefinitions $end
$comment Show the parameter values. $end
$dumpall
b11 V
b1 U
b10 T
b11 Q
b0 P
b1 O
b10 N
b11 K
b1 J
b0 I
b1 H
b10 G
b0 F
$end
#0
$dumpvars
bx a
bx `
bx _
bx ^
bx ]
bx \
bx [
bx Z
bx Y
bx X
bx W
bx S
bx R
bx M
bx L
bx E
bx D
bx C
bx B
bx A
bx @
bx ?
bx >
bx =
x<
x;
x:
bx 9
bx 8
bx 7
x6
x5
x4
bx 3
bx 2
bx 1
x0
bx /
bx .
x-
bx ,
b0 +
bx *
x)
bx (
1'
b0 &
0%
bx $
x#
x"
bx !
$end
#5000
0:
b101 1
b101 ]
0-
b101 $
b101 *
b101 =
b101 C
0)
b101 ?
b101 A
b100 2
b100 Z
b0 >
b0 B
b0 L
b0 (
b0 @
b0 /
b0 a
0#
06
05
0;
0"
04
1<
10
b10100 9
b1 R
b0 D
b10000 E
b101 _
b0 ^
b1 \
b10000 M
b101 8
b101 W
b1010000000100010000 7
b1010000000100010000 S
b1010000000100010000 X
b0 3
b0 Y
b0 [
1%
#10000
0'
0%
#15000
b1010 1
b1010 ]
b1010 $
b1010 *
b1010 =
b1010 C
b1010 ?
b1010 A
b1010 _
b10 \
b1010 8
b1010 W
b10100000001000010000 7
b10100000001000010000 S
b10100000001000010000 X
b1000 2
b1000 Z
b101100 9
b100 3
b100 Y
b100 [
1%
#20000
0%
#25000
b1111 1
b1111 ]
b1111 $
b1111 *
b1111 =
b1111 C
b1010 !
b1010 ,
b1010 .
b1010 `
b101 (
b101 @
b101 /
b101 a
0<
b1010 ?
b1010 A
b0 R
b0 E
b10 _
b1 ^
b11 \
b0 M
b0 8
b0 W
b100001001100000000 7
b100001001100000000 S
b100001001100000000 X
b1100 2
b1100 Z
b1000 9
b1000 3
b1000 Y
b1000 [
1%
#30000
0%
#35000
bx 1
bx ]
bx ?
bx A
x-
bx $
bx *
bx =
bx C
bx !
bx ,
bx .
bx `
bx (
bx @
bx /
bx a
00
x:
bx R
bx D
bx E
bx _
bx ^
bx \
bx M
bx 7
bx S
bx X
b10000 2
b10000 Z
b1100 9
b1100 3
b1100 Y
b1100 [
1%
#40000
0%
#45000
b10100 2
b10100 Z
b10000 9
b10000 3
b10000 Y
b10000 [
1%
#50000
0%
#55000
b11000 2
b11000 Z
b10100 9
b10100 3
b10100 Y
b10100 [
1%
#60000
0%
#65000
b11100 2
b11100 Z
b11000 9
b11000 3
b11000 Y
b11000 [
1%
