cpu/src/reg_file.v
module reg_file(
    input i_clk,
    input i_we,
    input i_rst,
    input [3:0] i_rd_addr,  // write destination
    input [31:0] i_rd_data, // write data
    input [3:0] i_rs1_addr, // port 1
    input [3:0] i_rs2_addr, // port 2
    output [31:0] o_rs1_data,
    output [31:0] o_rs2_data
);
    reg [31:0] regs[15:0]; // 16 - 32 bit general purpose registers
    // synchronous write
    always @(posedge i_clk) begin
        if (i_we && (i_rd_addr != 4'b0)) 
            regs[i_rd_addr] <= i_rd_data; 
    end

    // combinational read
    assign o_rs1_data = (i_rs1_addr == 4'b0) ? 32'b0 : regs[i_rs1_addr];
    assign o_rs2_data = (i_rs2_addr == 4'b0) ? 32'b0 : regs[i_rs2_addr];
endmodule

cpu/testbenches/reg_file_tb.v
module reg_file_tb;
    /*
    input i_clk,
    input i_we,
    input i_rst,
    input [3:0] i_rd_addr,  // write destination
    input [31:0] i_rd_data, // write data
    input [3:0] i_rs1_addr, // port 1
    input [3:0] i_rs2_addr, // port 2
    output [31:0] o_rs1_data,
    output [31:0] o_rs2_data
    */    
    reg clk = 0;
    reg we;
    reg [3:0] rd_addr, rs1_addr, rs2_addr;
    reg [31:0] rd_data;
    wire [31:0] rs1_data, rs2_data;

    always #1 clk = ~clk;
    
    reg_file UUT(clk, we, 1'b0, rd_addr, rd_data, rs1_addr, rs2_addr, rs1_data, rs2_data);

    initial begin
        $dumpfile("reg_file.vcd");
        $dumpvars(0, reg_file_tb);
        $monitor("t=%0t we=%b rd_addr=%d rd_data=%d | rs1=%d->%d rs2=%d->%d",
                  $time, we, rd_addr, rd_data, rs1_addr, rs1_data, rs2_addr, rs2_data);
        
        // initialize initial state
        we = 0; rd_addr = 0; rd_data = 0; rs1_addr = 4'd15; rs2_addr = 4'd8;
        @(negedge clk);

        // write to register 15
        we = 1; rd_addr = 4'hF; rd_data = 32'd42;
        @(negedge clk);

        // write to register 8
        rd_addr = 4'h8; rd_data = 32'd67;
        @(negedge clk);

        // write to register 0
        rd_addr = 4'h0; rd_data = 32'd15;
        @(negedge clk);

        we = 0;
        @(negedge clk);

        // attempt to write into register 1, we = 0;
        rd_addr = 4'hF; rd_data = 32'd63;
        @(negedge clk);

        $finish;
    end
endmodule

cpu/sim/reg_file.vcd
$date
	Wed Aug 26 19:41:39 2026
$end
$version
	Icarus Verilog
$end
$timescale
	1s
$end
$scope module reg_file_tb $end
$var wire 32 ! rs2_data [31:0] $end
$var wire 32 " rs1_data [31:0] $end
$var reg 1 # clk $end
$var reg 4 $ rd_addr [3:0] $end
$var reg 32 % rd_data [31:0] $end
$var reg 4 & rs1_addr [3:0] $end
$var reg 4 ' rs2_addr [3:0] $end
$var reg 1 ( we $end
$scope module UUT $end
$var wire 1 # i_clk $end
$var wire 4 ) i_rd_addr [3:0] $end
$var wire 32 * i_rd_data [31:0] $end
$var wire 4 + i_rs1_addr [3:0] $end
$var wire 4 , i_rs2_addr [3:0] $end
$var wire 1 - i_rst $end
$var wire 1 ( i_we $end
$var wire 32 . o_rs1_data [31:0] $end
$var wire 32 / o_rs2_data [31:0] $end
$upscope $end
$upscope $end
$enddefinitions $end
$comment Show the parameter values. $end
$dumpall
$end
#0
$dumpvars
bx /
bx .
0-
b1000 ,
b1111 +
b0 *
b0 )
0(
b1000 '
b1111 &
b0 %
b0 $
0#
bx "
bx !
$end
#1
1#
#2
b101010 %
b101010 *
b1111 $
b1111 )
1(
0#
#3
b101010 "
b101010 .
1#
#4
b1000011 %
b1000011 *
b1000 $
b1000 )
0#
#5
b1000011 !
b1000011 /
1#
#6
b1111 %
b1111 *
b0 $
b0 )
0#
#7
1#
#8
0(
0#
#9
1#
#10
b111111 %
b111111 *
b1111 $
b1111 )
0#
