uart/transmitter/uart_tx.v
// UART Transmitter for Tang Nano 9k
// 27 MHz Clock --> 115200 baud rate; ~234 CLKS_PER_BIT
module uart_tx
    #(parameter CLKS_PER_BIT = 234)

    (
      input i_Clock,
      input i_Tx_DV, // data valid (answer from driving line high)
      input [7:0] i_Tx_Byte,
      output o_Tx_Active,
      output reg o_Tx_Serial,
      output o_Tx_Done
    );

    parameter s_IDLE            = 3'b000;
    parameter s_TX_START_BIT    = 3'b001;
    parameter s_TX_DATA_BITS    = 3'b010;
    parameter s_TX_STOP_BIT     = 3'b011;
    parameter s_CLEANUP         = 3'b100;

    reg [2:0] r_SM_Main     = 0; // holds current state of UART transmiotter
    reg [7:0] r_Clock_Count = 0; // holds clock cycles within the current bit period
    reg [2:0] r_Bit_Index   = 0; // which one of the 8 data bits is being transmitted
    reg [7:0] r_Tx_Data     = 0; // copy of i_Tx_Byte --> prevents corruption of i_Tx_byte
    reg r_Tx_Done           = 0; // flag --> finished sending byte
    reg r_Tx_Active         = 0; // flag --> high during transmission, low du ring idle

    always @(posedge i_Clock) begin
    case (r_SM_Main)
      s_IDLE: begin
        // TODO: what should the line do while idle?
        o_Tx_Serial <= 1'b1; // drive the line high while idle
        r_Tx_Done   <= 1'b0; // reset; byte transmission ready to begin
        r_Clock_Count <= 0; // reset the clock count
        r_Bit_Index <= 0; // reset the bit index

        // TODO: what should happen when i_Tx_DV pulses?
        if (i_Tx_DV == 1'b1) begin
            r_Tx_Active <= 1'b1; // show line is active
            r_Tx_Data <= i_Tx_Byte; // data to send is i_Tx_Byte;
            r_SM_Main <= s_TX_START_BIT; // set state to (START_BIT)
        end
      end

      s_TX_START_BIT: begin
        // TODO: drive the line low, count one bit period
        o_Tx_Serial <= 1'b0; //drive the line low

        // wait for one bit period before sending data 
        if (r_Clock_Count < CLKS_PER_BIT-1) begin
            r_Clock_Count <= r_Clock_Count + 1;
            r_SM_Main <= s_TX_START_BIT; // remain in s_TX_START_BIT
        end else begin
            r_Clock_Count <= 0;
            r_SM_Main <= s_TX_DATA_BITS;
        end
      end

      s_TX_DATA_BITS: begin
        // TODO: shift r_Tx_Data out one bit at a time
        o_Tx_Serial <= r_Tx_Data[r_Bit_Index];

        if (r_Clock_Count < CLKS_PER_BIT-1) begin
            r_Clock_Count <= r_Clock_Count + 1;
            r_SM_Main <= s_TX_DATA_BITS;
        end else begin
            r_Clock_Count <= 0;

            // Check if we have sent all bits in a data packet
            if (r_Bit_Index < 7) begin
                r_Bit_Index <= r_Bit_Index + 1;
                r_SM_Main <= s_TX_DATA_BITS;
            end else begin 
                // all data bits sent out; reset r_BIT, and transition to next state
                r_Bit_Index <= 0;
                r_SM_Main <= s_TX_STOP_BIT;
            end
        end
      end

      s_TX_STOP_BIT: begin
        // TODO: drive line high, count one bit period, signal done
        o_Tx_Serial <= 1;
        
        if (r_Clock_Count < CLKS_PER_BIT-1) begin
            r_Clock_Count <= r_Clock_Count + 1;
            r_SM_Main <= s_TX_STOP_BIT;
        end else begin 
            r_Tx_Done <= 1'b1;
            r_Clock_Count <= 0;
            r_SM_Main <= s_CLEANUP;
            r_Tx_Active <= 1'b0;
        end
      end

      s_CLEANUP: begin
        // TODO: one-cycle pause back to IDLE
        r_Tx_Done <= 1'b1;
        r_SM_Main <= s_IDLE;
      end

      default: r_SM_Main <= s_IDLE;
    endcase
  end

  assign o_Tx_Active = r_Tx_Active;
  assign o_Tx_Done   = r_Tx_Done;

endmodule

uart/transmitter/uart_tx_tb.v
`timescale 1ns/1ps

module uart_tx_tb;

    // Testbench signals
    reg        r_Clock = 0;
    reg        r_Tx_DV = 0;
    reg  [7:0] r_Tx_Byte = 0;
    wire       w_Tx_Active;
    wire       w_Tx_Serial;
    wire       w_Tx_Done;

    // Instantiate the UART transmitter
    uart_tx #(.CLKS_PER_BIT(234)) UUT (
        .i_Clock     (r_Clock),
        .i_Tx_DV     (r_Tx_DV),
        .i_Tx_Byte   (r_Tx_Byte),
        .o_Tx_Active (w_Tx_Active),
        .o_Tx_Serial (w_Tx_Serial),
        .o_Tx_Done   (w_Tx_Done)
    );

    // Clock generation — 27 MHz means a period of ~37.037 ns.
    // TODO: toggle r_Clock every half-period to build that clock.
    always begin
        // #(half_period) r_Clock = ~r_Clock;
        #(18.5) r_Clock = ~r_Clock;
    end

    always @(posedge r_Clock) begin
        if (UUT.r_SM_Main == UUT.s_TX_STOP_BIT)
            $display("Time=%0t | STOP_BIT, count=%0d", $time, UUT.r_Clock_Count);
    end

    // Waveform dump so you can view this in GTKWave
    initial begin
        $dumpfile("uart_tx_tb.vcd");
        $dumpvars(0, uart_tx_tb);
    end

    // Stimulus
    initial begin
        // TODO 1: wait a few clock edges to let things settle
        @(posedge r_Clock);
        @(posedge r_Clock);

        // TODO 2: pick a byte with mixed 1s and 0s, e.g. 8'b10110101,
        //         and load it onto r_Tx_Byte
        r_Tx_Byte <= 8'b10110101;

        // TODO 3: pulse r_Tx_DV high for exactly one clock cycle
        //         (remember: it needs to go back low after — this isn't
        //         a level signal, it's a one-cycle trigger)
        @(posedge r_Clock);
        r_Tx_DV <= 1'b1;
        @(posedge r_Clock);
        r_Tx_DV <=1'b0;

        // TODO 4: wait long enough for a full frame to transmit
        //         (~10 * CLKS_PER_BIT clocks: start + 8 data + stop),
        //         or better — wait until w_Tx_Done goes high
        @(posedge w_Tx_Done);
        #20;
        // TODO 5: end simulation
        $finish;
    end

endmodule

uart/transmitter_files/uart_tx_tb.vcd
$date
	Sun Aug 23 21:49:04 2026
$end
$version
	Icarus Verilog
$end
$timescale
	1ps
$end
$scope module uart_tx_tb $end
$var wire 1 ! w_Tx_Serial $end
$var wire 1 " w_Tx_Done $end
$var wire 1 # w_Tx_Active $end
$var reg 1 $ r_Clock $end
$var reg 8 % r_Tx_Byte [7:0] $end
$var reg 1 & r_Tx_DV $end
$scope module UUT $end
$var wire 1 $ i_Clock $end
$var wire 8 ' i_Tx_Byte [7:0] $end
$var wire 1 & i_Tx_DV $end
$var wire 1 # o_Tx_Active $end
$var wire 1 " o_Tx_Done $end
$var parameter 32 ( CLKS_PER_BIT $end
$var parameter 3 ) s_CLEANUP $end
$var parameter 3 * s_IDLE $end
$var parameter 3 + s_TX_DATA_BITS $end
$var parameter 3 , s_TX_START_BIT $end
$var parameter 3 - s_TX_STOP_BIT $end
$var reg 1 ! o_Tx_Serial $end
$var reg 3 . r_Bit_Index [2:0] $end
$var reg 8 / r_Clock_Count [7:0] $end
$var reg 3 0 r_SM_Main [2:0] $end
$var reg 1 1 r_Tx_Active $end
$var reg 8 2 r_Tx_Data [7:0] $end
$var reg 1 3 r_Tx_Done $end
$upscope $end
$upscope $end
$enddefinitions $end
$comment Show the parameter values. $end
$dumpall
b11 -
b1 ,
b10 +
b0 *
b100 )
b11101010 (
$end
#0
$dumpvars
03
b0 2
01
b0 0
b0 /
b0 .
b0 '
0&
b0 %
0$
0#
0"
x!
$end
#18500
1!
1$
#37000
0$
#55500
b10110101 %
b10110101 '
1$
#74000
0$
#92500
1&
1$
#111000
0$
#129500
0&
b1 0
b10110101 2
1#
11
1$
#148000
0$
#166500
b1 /
0!
1$
#185000
0$
#203500
b10 /
1$
#222000
0$
#240500
b11 /
1$
#259000
0$
#277500
b100 /
1$
#296000
0$
#314500
b101 /
1$
#333000
0$
#351500
b110 /
1$
#370000
0$
#388500
b111 /
1$
#407000
0$
#425500
b1000 /
1$
#444000
0$
#462500
b1001 /
1$
#481000
0$
#499500
b1010 /
1$
#518000
0$
#536500
b1011 /
1$
#555000
0$
#573500
b1100 /
1$
#592000
0$
#610500
b1101 /
1$
#629000
0$
#647500
b1110 /
1$
#666000
0$
#684500
b1111 /
1$
#703000
0$
#721500
b10000 /
1$
#740000
0$
#758500
b10001 /
1$
#777000
0$
#795500
b10010 /
1$
#814000
0$
#832500
b10011 /
1$
#851000
0$
#869500
b10100 /
1$
#888000
0$
#906500
b10101 /
1$
#925000
0$
#943500
b10110 /
1$
#962000
0$
#980500
b10111 /
1$
#999000
0$
#1017500
b11000 /
1$
#1036000
0$
#1054500
b11001 /
1$
#1073000
0$
#1091500
b11010 /
1$
#1110000
0$
#1128500
b11011 /
1$
#1147000
0$
#1165500
b11100 /
1$
#1184000
0$
#1202500
b11101 /
1$
#1221000
0$
#1239500
b11110 /
1$
#1258000
0$
#1276500
b11111 /
1$
#1295000
0$
#1313500
b100000 /
1$
#1332000
0$
#1350500
b100001 /
1$
#1369000
0$
#1387500
b100010 /
1$
#1406000
0$
#1424500
b100011 /
1$
#1443000
0$
#1461500
b100100 /
1$
#1480000
0$
#1498500
b100101 /
1$
#1517000
0$
#1535500
b100110 /
1$
#1554000
0$
#1572500
b100111 /
1$
#1591000
0$
#1609500
b101000 /
1$
#1628000
0$
#1646500
b101001 /
1$
#1665000
0$
#1683500
b101010 /
1$
#1702000
0$
#1720500
b101011 /
1$
#1739000
0$
#1757500
b101100 /
1$
#1776000
0$
#1794500
b101101 /
1$
#1813000
0$
#1831500
b101110 /
1$
#1850000
0$
#1868500
b101111 /
1$
#1887000
0$
#1905500
b110000 /
1$
#1924000
0$
#1942500
b110001 /
1$
#1961000
0$
#1979500
b110010 /
1$
#1998000
0$
#2016500
b110011 /
1$
#2035000
0$
#2053500
b110100 /
1$
#2072000
0$
#2090500
b110101 /
1$
#2109000
0$
#2127500
b110110 /
1$
#2146000
0$
#2164500
b110111 /
1$
#2183000
0$
#2201500
b111000 /
1$
#2220000
0$
#2238500
b111001 /
1$
#2257000
0$
#2275500
b111010 /
1$
#2294000
0$
#2312500
b111011 /
1$
#2331000
0$
#2349500
b111100 /
1$
#2368000
0$
#2386500
b111101 /
1$
#2405000
0$
#2423500
b111110 /
1$
#2442000
0$
#2460500
b111111 /
1$
#2479000
0$
#2497500
b1000000 /
1$
#2516000
0$
#2534500
b1000001 /
1$
#2553000
0$
#2571500
b1000010 /
1$
#2590000
0$
#2608500
b1000011 /
1$
#2627000
0$
#2645500
b1000100 /
1$
#2664000
0$
#2682500
b1000101 /
1$
#2701000
0$
#2719500
b1000110 /
1$
#2738000
0$
#2756500
b1000111 /
1$
#2775000
0$
#2793500
b1001000 /
1$
#2812000
0$
#2830500
b1001001 /
1$
#2849000
0$
#2867500
b1001010 /
1$
#2886000
0$
#2904500
b1001011 /
1$
#2923000
0$
#2941500
b1001100 /
1$
#2960000
0$
#2978500
b1001101 /
1$
#2997000
0$
#3015500
b1001110 /
1$
#3034000
0$
#3052500
b1001111 /
1$
#3071000
0$
#3089500
b1010000 /
1$
#3108000
0$
#3126500
b1010001 /
1$
#3145000
0$
#3163500
b1010010 /
1$
#3182000
0$
#3200500
b1010011 /
1$
#3219000
0$
#3237500
b1010100 /
1$
#3256000
0$
#3274500
b1010101 /
1$
#3293000
0$
#3311500
b1010110 /
1$
#3330000
0$
#3348500
b1010111 /
1$
#3367000
0$
#3385500
b1011000 /
1$
#3404000
0$
#3422500
b1011001 /
1$
#3441000
0$
#3459500
b1011010 /
1$
#3478000
0$
#3496500
b1011011 /
1$
#3515000
0$
#3533500
b1011100 /
1$
#3552000
0$
#3570500
b1011101 /
1$
#3589000
0$
#3607500
b1011110 /
1$
#3626000
0$
#3644500
b1011111 /
1$
#3663000
0$
#3681500
b1100000 /
1$
#3700000
0$
#3718500
b1100001 /
1$
#3737000
0$
#3755500
b1100010 /
1$
#3774000
0$
#3792500
b1100011 /
1$
#3811000
0$
#3829500
b1100100 /
1$
#3848000
0$
#3866500
b1100101 /
1$
#3885000
0$
#3903500
b1100110 /
1$
#3922000
0$
#3940500
b1100111 /
1$
#3959000
0$
#3977500
b1101000 /
1$
#3996000
0$
#4014500
b1101001 /
1$
#4033000
0$
#4051500
b1101010 /
1$
#4070000
0$
#4088500
b1101011 /
1$
#4107000
0$
#4125500
b1101100 /
1$
#4144000
0$
#4162500
b1101101 /
1$
#4181000
0$
#4199500
b1101110 /
1$
#4218000
0$
#4236500
b1101111 /
1$
#4255000
0$
#4273500
b1110000 /
1$
#4292000
0$
#4310500
b1110001 /
1$
#4329000
0$
#4347500
b1110010 /
1$
#4366000
0$
#4384500
b1110011 /
1$
#4403000
0$
#4421500
b1110100 /
1$
#4440000
0$
#4458500
b1110101 /
1$
#4477000
0$
#4495500
b1110110 /
1$
#4514000
0$
#4532500
b1110111 /
1$
#4551000
0$
#4569500
b1111000 /
1$
#4588000
0$
#4606500
b1111001 /
1$
#4625000
0$
#4643500
b1111010 /
1$
#4662000
0$
#4680500
b1111011 /
1$
#4699000
0$
#4717500
b1111100 /
1$
#4736000
0$
#4754500
b1111101 /
1$
#4773000
0$
#4791500
b1111110 /
1$
#4810000
0$
#4828500
b1111111 /
1$
#4847000
0$
#4865500
b10000000 /
1$
#4884000
0$
#4902500
b10000001 /
1$
#4921000
0$
#4939500
b10000010 /
1$
#4958000
0$
#4976500
b10000011 /
1$
#4995000
0$
#5013500
b10000100 /
1$
#5032000
0$
#5050500
b10000101 /
1$
#5069000
0$
#5087500
b10000110 /
1$
#5106000
0$
#5124500
b10000111 /
1$
#5143000
0$
#5161500
b10001000 /
1$
#5180000
0$
#5198500
b10001001 /
1$
#5217000
0$
#5235500
b10001010 /
1$
#5254000
0$
#5272500
b10001011 /
1$
#5291000
0$
#5309500
b10001100 /
1$
#5328000
0$
#5346500
b10001101 /
1$
#5365000
0$
#5383500
b10001110 /
1$
#5402000
0$
#5420500
b10001111 /
1$
#5439000
0$
#5457500
b10010000 /
1$
#5476000
0$
#5494500
b10010001 /
1$
#5513000
0$
#5531500
b10010010 /
1$
#5550000
0$
#5568500
b10010011 /
1$
#5587000
0$
#5605500
b10010100 /
1$
#5624000
0$
#5642500
b10010101 /
1$
#5661000
0$
#5679500
b10010110 /
1$
#5698000
0$
#5716500
b10010111 /
1$
#5735000
0$
#5753500
b10011000 /
1$
#5772000
0$
#5790500
b10011001 /
1$
#5809000
0$
#5827500
b10011010 /
1$
#5846000
0$
#5864500
b10011011 /
1$
#5883000
0$
#5901500
b10011100 /
1$
#5920000
0$
#5938500
b10011101 /
1$
#5957000
0$
#5975500
b10011110 /
1$
#5994000
0$
#6012500
b10011111 /
1$
#6031000
0$
#6049500
b10100000 /
1$
#6068000
0$
#6086500
b10100001 /
1$
#6105000
0$
#6123500
b10100010 /
1$
#6142000
0$
#6160500
b10100011 /
1$
#6179000
0$
#6197500
b10100100 /
1$
#6216000
0$
#6234500
b10100101 /
1$
#6253000
0$
#6271500
b10100110 /
1$
#6290000
0$
#6308500
b10100111 /
1$
#6327000
0$
#6345500
b10101000 /
1$
#6364000
0$
#6382500
b10101001 /
1$
#6401000
0$
#6419500
b10101010 /
1$
#6438000
0$
#6456500
b10101011 /
1$
#6475000
0$
#6493500
b10101100 /
1$
#6512000
0$
#6530500
b10101101 /
1$
#6549000
0$
#6567500
b10101110 /
1$
#6586000
0$
#6604500
b10101111 /
1$
#6623000
0$
#6641500
b10110000 /
1$
#6660000
0$
#6678500
b10110001 /
1$
#6697000
0$
#6715500
b10110010 /
1$
#6734000
0$
#6752500
b10110011 /
1$
#6771000
0$
#6789500
b10110100 /
1$
#6808000
0$
#6826500
b10110101 /
1$
#6845000
0$
#6863500
b10110110 /
1$
#6882000
0$
#6900500
b10110111 /
1$
#6919000
0$
#6937500
b10111000 /
1$
#6956000
0$
#6974500
b10111001 /
1$
#6993000
0$
#7011500
b10111010 /
1$
#7030000
0$
#7048500
b10111011 /
1$
#7067000
0$
#7085500
b10111100 /
1$
#7104000
0$
#7122500
b10111101 /
1$
#7141000
0$
#7159500
b10111110 /
1$
#7178000
0$
#7196500
b10111111 /
1$
#7215000
0$
#7233500
b11000000 /
1$
#7252000
0$
#7270500
b11000001 /
1$
#7289000
0$
#7307500
b11000010 /
1$
#7326000
0$
#7344500
b11000011 /
1$
#7363000
0$
#7381500
b11000100 /
1$
#7400000
0$
#7418500
b11000101 /
1$
#7437000
0$
#7455500
b11000110 /
1$
#7474000
0$
#7492500
b11000111 /
1$
#7511000
0$
#7529500
b11001000 /
1$
#7548000
0$
#7566500
b11001001 /
1$
#7585000
0$
#7603500
b11001010 /
1$
#7622000
0$
#7640500
b11001011 /
1$
#7659000
0$
#7677500
b11001100 /
1$
#7696000
0$
#7714500
b11001101 /
1$
#7733000
0$
#7751500
b11001110 /
1$
#7770000
0$
#7788500
b11001111 /
1$
#7807000
0$
#7825500
b11010000 /
1$
#7844000
0$
#7862500
b11010001 /
1$
#7881000
0$
#7899500
b11010010 /
1$
#7918000
0$
#7936500
b11010011 /
1$
#7955000
0$
#7973500
b11010100 /
1$
#7992000
0$
#8010500
b11010101 /
1$
#8029000
0$
#8047500
b11010110 /
1$
#8066000
0$
#8084500
b11010111 /
1$
#8103000
0$
#8121500
b11011000 /
1$
#8140000
0$
#8158500
b11011001 /
1$
#8177000
0$
#8195500
b11011010 /
1$
#8214000
0$
#8232500
b11011011 /
1$
#8251000
0$
#8269500
b11011100 /
1$
#8288000
0$
#8306500
b11011101 /
1$
#8325000
0$
#8343500
b11011110 /
1$
#8362000
0$
#8380500
b11011111 /
1$
#8399000
0$
#8417500
b11100000 /
1$
#8436000
0$
#8454500
b11100001 /
1$
#8473000
0$
#8491500
b11100010 /
1$
#8510000
0$
#8528500
b11100011 /
1$
#8547000
0$
#8565500
b11100100 /
1$
#8584000
0$
#8602500
b11100101 /
1$
#8621000
0$
#8639500
b11100110 /
1$
#8658000
0$
#8676500
b11100111 /
1$
#8695000
0$
#8713500
b11101000 /
1$
#8732000
0$
#8750500
b11101001 /
1$
#8769000
0$
#8787500
b10 0
b0 /
1$
#8806000
0$
#8824500
b1 /
1!
1$
#8843000
0$
#8861500
b10 /
1$
#8880000
0$
#8898500
b11 /
1$
#8917000
0$
#8935500
b100 /
1$
#8954000
0$
#8972500
b101 /
1$
#8991000
0$
#9009500
b110 /
1$
#9028000
0$
#9046500
b111 /
1$
#9065000
0$
#9083500
b1000 /
1$
#9102000
0$
#9120500
b1001 /
1$
#9139000
0$
#9157500
b1010 /
1$
#9176000
0$
#9194500
b1011 /
1$
#9213000
0$
#9231500
b1100 /
1$
#9250000
0$
#9268500
b1101 /
1$
#9287000
0$
#9305500
b1110 /
1$
#9324000
0$
#9342500
b1111 /
1$
#9361000
0$
#9379500
b10000 /
1$
#9398000
0$
#9416500
b10001 /
1$
#9435000
0$
#9453500
b10010 /
1$
#9472000
0$
#9490500
b10011 /
1$
#9509000
0$
#9527500
b10100 /
1$
#9546000
0$
#9564500
b10101 /
1$
#9583000
0$
#9601500
b10110 /
1$
#9620000
0$
#9638500
b10111 /
1$
#9657000
0$
#9675500
b11000 /
1$
#9694000
0$
#9712500
b11001 /
1$
#9731000
0$
#9749500
b11010 /
1$
#9768000
0$
#9786500
b11011 /
1$
#9805000
0$
#9823500
b11100 /
1$
#9842000
0$
#9860500
b11101 /
1$
#9879000
0$
#9897500
b11110 /
1$
#9916000
0$
#9934500
b11111 /
1$
#9953000
0$
#9971500
b100000 /
1$
#9990000
0$
#10008500
b100001 /
1$
#10027000
0$
#10045500
b100010 /
1$
#10064000
0$
#10082500
b100011 /
1$
#10101000
0$
#10119500
b100100 /
1$
#10138000
0$
#10156500
b100101 /
1$
#10175000
0$
#10193500
b100110 /
1$
#10212000
0$
#10230500
b100111 /
1$
#10249000
0$
#10267500
b101000 /
1$
#10286000
0$
#10304500
b101001 /
1$
#10323000
0$
#10341500
b101010 /
1$
#10360000
0$
#10378500
b101011 /
1$
#10397000
0$
#10415500
b101100 /
1$
#10434000
0$
#10452500
b101101 /
1$
#10471000
0$
#10489500
b101110 /
1$
#10508000
0$
#10526500
b101111 /
1$
#10545000
0$
#10563500
b110000 /
1$
#10582000
0$
#10600500
b110001 /
1$
#10619000
0$
#10637500
b110010 /
1$
#10656000
0$
#10674500
b110011 /
1$
#10693000
0$
#10711500
b110100 /
1$
#10730000
0$
#10748500
b110101 /
1$
#10767000
0$
#10785500
b110110 /
1$
#10804000
0$
#10822500
b110111 /
1$
#10841000
0$
#10859500
b111000 /
1$
#10878000
0$
#10896500
b111001 /
1$
#10915000
0$
#10933500
b111010 /
1$
#10952000
0$
#10970500
b111011 /
1$
#10989000
0$
#11007500
b111100 /
1$
#11026000
0$
#11044500
b111101 /
1$
#11063000
0$
#11081500
b111110 /
1$
#11100000
0$
#11118500
b111111 /
1$
#11137000
0$
#11155500
b1000000 /
1$
#11174000
0$
#11192500
b1000001 /
1$
#11211000
0$
#11229500
b1000010 /
1$
#11248000
0$
#11266500
b1000011 /
1$
#11285000
0$
#11303500
b1000100 /
1$
#11322000
0$
#11340500
b1000101 /
1$
#11359000
0$
#11377500
b1000110 /
1$
#11396000
0$
#11414500
b1000111 /
1$
#11433000
0$
#11451500
b1001000 /
1$
#11470000
0$
#11488500
b1001001 /
1$
#11507000
0$
#11525500
b1001010 /
1$
#11544000
0$
#11562500
b1001011 /
1$
#11581000
0$
#11599500
b1001100 /
1$
#11618000
0$
#11636500
b1001101 /
1$
#11655000
0$
#11673500
b1001110 /
1$
#11692000
0$
#11710500
b1001111 /
1$
#11729000
0$
#11747500
b1010000 /
1$
#11766000
0$
#11784500
b1010001 /
1$
#11803000
0$
#11821500
b1010010 /
1$
#11840000
0$
#11858500
b1010011 /
1$
#11877000
0$
#11895500
b1010100 /
1$
#11914000
0$
#11932500
b1010101 /
1$
#11951000
0$
#11969500
b1010110 /
1$
#11988000
0$
#12006500
b1010111 /
1$
#12025000
0$
#12043500
b1011000 /
1$
#12062000
0$
#12080500
b1011001 /
1$
#12099000
0$
#12117500
b1011010 /
1$
#12136000
0$
#12154500
b1011011 /
1$
#12173000
0$
#12191500
b1011100 /
1$
#12210000
0$
#12228500
b1011101 /
1$
#12247000
0$
#12265500
b1011110 /
1$
#12284000
0$
#12302500
b1011111 /
1$
#12321000
0$
#12339500
b1100000 /
1$
#12358000
0$
#12376500
b1100001 /
1$
#12395000
0$
#12413500
b1100010 /
1$
#12432000
0$
#12450500
b1100011 /
1$
#12469000
0$
#12487500
b1100100 /
1$
#12506000
0$
#12524500
b1100101 /
1$
#12543000
0$
#12561500
b1100110 /
1$
#12580000
0$
#12598500
b1100111 /
1$
#12617000
0$
#12635500
b1101000 /
1$
#12654000
0$
#12672500
b1101001 /
1$
#12691000
0$
#12709500
b1101010 /
1$
#12728000
0$
#12746500
b1101011 /
1$
#12765000
0$
#12783500
b1101100 /
1$
#12802000
0$
#12820500
b1101101 /
1$
#12839000
0$
#12857500
b1101110 /
1$
#12876000
0$
#12894500
b1101111 /
1$
#12913000
0$
#12931500
b1110000 /
1$
#12950000
0$
#12968500
b1110001 /
1$
#12987000
0$
#13005500
b1110010 /
1$
#13024000
0$
#13042500
b1110011 /
1$
#13061000
0$
#13079500
b1110100 /
1$
#13098000
0$
#13116500
b1110101 /
1$
#13135000
0$
#13153500
b1110110 /
1$
#13172000
0$
#13190500
b1110111 /
1$
#13209000
0$
#13227500
b1111000 /
1$
#13246000
0$
#13264500
b1111001 /
1$
#13283000
0$
#13301500
b1111010 /
1$
#13320000
0$
#13338500
b1111011 /
1$
#13357000
0$
#13375500
b1111100 /
1$
#13394000
0$
#13412500
b1111101 /
1$
#13431000
0$
#13449500
b1111110 /
1$
#13468000
0$
#13486500
b1111111 /
1$
#13505000
0$
#13523500
b10000000 /
1$
#13542000
0$
#13560500
b10000001 /
1$
#13579000
0$
#13597500
b10000010 /
1$
#13616000
0$
#13634500
b10000011 /
1$
#13653000
0$
#13671500
b10000100 /
1$
#13690000
0$
#13708500
b10000101 /
1$
#13727000
0$
#13745500
b10000110 /
1$
#13764000
0$
#13782500
b10000111 /
1$
#13801000
0$
#13819500
b10001000 /
1$
#13838000
0$
#13856500
b10001001 /
1$
#13875000
0$
#13893500
b10001010 /
1$
#13912000
0$
#13930500
b10001011 /
1$
#13949000
0$
#13967500
b10001100 /
1$
#13986000
0$
#14004500
b10001101 /
1$
#14023000
0$
#14041500
b10001110 /
1$
#14060000
0$
#14078500
b10001111 /
1$
#14097000
0$
#14115500
b10010000 /
1$
#14134000
0$
#14152500
b10010001 /
1$
#14171000
0$
#14189500
b10010010 /
1$
#14208000
0$
#14226500
b10010011 /
1$
#14245000
0$
#14263500
b10010100 /
1$
#14282000
0$
#14300500
b10010101 /
1$
#14319000
0$
#14337500
b10010110 /
1$
#14356000
0$
#14374500
b10010111 /
1$
#14393000
0$
#14411500
b10011000 /
1$
#14430000
0$
#14448500
b10011001 /
1$
#14467000
0$
#14485500
b10011010 /
1$
#14504000
0$
#14522500
b10011011 /
1$
#14541000
0$
#14559500
b10011100 /
1$
#14578000
0$
#14596500
b10011101 /
1$
#14615000
0$
#14633500
b10011110 /
1$
#14652000
0$
#14670500
b10011111 /
1$
#14689000
0$
#14707500
b10100000 /
1$
#14726000
0$
#14744500
b10100001 /
1$
#14763000
0$
#14781500
b10100010 /
1$
#14800000
0$
#14818500
b10100011 /
1$
#14837000
0$
#14855500
b10100100 /
1$
#14874000
0$
#14892500
b10100101 /
1$
#14911000
0$
#14929500
b10100110 /
1$
#14948000
0$
#14966500
b10100111 /
1$
#14985000
0$
#15003500
b10101000 /
1$
#15022000
0$
#15040500
b10101001 /
1$
#15059000
0$
#15077500
b10101010 /
1$
#15096000
0$
#15114500
b10101011 /
1$
#15133000
0$
#15151500
b10101100 /
1$
#15170000
0$
#15188500
b10101101 /
1$
#15207000
0$
#15225500
b10101110 /
1$
#15244000
0$
#15262500
b10101111 /
1$
#15281000
0$
#15299500
b10110000 /
1$
#15318000
0$
#15336500
b10110001 /
1$
#15355000
0$
#15373500
b10110010 /
1$
#15392000
0$
#15410500
b10110011 /
1$
#15429000
0$
#15447500
b10110100 /
1$
#15466000
0$
#15484500
b10110101 /
1$
#15503000
0$
#15521500
b10110110 /
1$
#15540000
0$
#15558500
b10110111 /
1$
#15577000
0$
#15595500
b10111000 /
1$
#15614000
0$
#15632500
b10111001 /
1$
#15651000
0$
#15669500
b10111010 /
1$
#15688000
0$
#15706500
b10111011 /
1$
#15725000
0$
#15743500
b10111100 /
1$
#15762000
0$
#15780500
b10111101 /
1$
#15799000
0$
#15817500
b10111110 /
1$
#15836000
0$
#15854500
b10111111 /
1$
#15873000
0$
#15891500
b11000000 /
1$
#15910000
0$
#15928500
b11000001 /
1$
#15947000
0$
#15965500
b11000010 /
1$
#15984000
0$
#16002500
b11000011 /
1$
#16021000
0$
#16039500
b11000100 /
1$
#16058000
0$
#16076500
b11000101 /
1$
#16095000
0$
#16113500
b11000110 /
1$
#16132000
0$
#16150500
b11000111 /
1$
#16169000
0$
#16187500
b11001000 /
1$
#16206000
0$
#16224500
b11001001 /
1$
#16243000
0$
#16261500
b11001010 /
1$
#16280000
0$
#16298500
b11001011 /
1$
#16317000
0$
#16335500
b11001100 /
1$
#16354000
0$
#16372500
b11001101 /
1$
#16391000
0$
#16409500
b11001110 /
1$
#16428000
0$
#16446500
b11001111 /
1$
#16465000
0$
#16483500
b11010000 /
1$
#16502000
0$
#16520500
b11010001 /
1$
#16539000
0$
#16557500
b11010010 /
1$
#16576000
0$
#16594500
b11010011 /
1$
#16613000
0$
#16631500
b11010100 /
1$
#16650000
0$
#16668500
b11010101 /
1$
#16687000
0$
#16705500
b11010110 /
1$
#16724000
0$
#16742500
b11010111 /
1$
#16761000
0$
#16779500
b11011000 /
1$
#16798000
0$
#16816500
b11011001 /
1$
#16835000
0$
#16853500
b11011010 /
1$
#16872000
0$
#16890500
b11011011 /
1$
#16909000
0$
#16927500
b11011100 /
1$
#16946000
0$
#16964500
b11011101 /
1$
#16983000
0$
#17001500
b11011110 /
1$
#17020000
0$
#17038500
b11011111 /
1$
#17057000
0$
#17075500
b11100000 /
1$
#17094000
0$
#17112500
b11100001 /
1$
#17131000
0$
#17149500
b11100010 /
1$
#17168000
0$
#17186500
b11100011 /
1$
#17205000
0$
#17223500
b11100100 /
1$
#17242000
0$
#17260500
b11100101 /
1$
#17279000
0$
#17297500
b11100110 /
1$
#17316000
0$
#17334500
b11100111 /
1$
#17353000
0$
#17371500
b11101000 /
1$
#17390000
0$
#17408500
b11101001 /
1$
#17427000
0$
#17445500
b1 .
b0 /
1$
#17464000
0$
#17482500
b1 /
0!
1$
#17501000
0$
#17519500
b10 /
1$
#17538000
0$
#17556500
b11 /
1$
#17575000
0$
#17593500
b100 /
1$
#17612000
0$
#17630500
b101 /
1$
#17649000
0$
#17667500
b110 /
1$
#17686000
0$
#17704500
b111 /
1$
#17723000
0$
#17741500
b1000 /
1$
#17760000
0$
#17778500
b1001 /
1$
#17797000
0$
#17815500
b1010 /
1$
#17834000
0$
#17852500
b1011 /
1$
#17871000
0$
#17889500
b1100 /
1$
#17908000
0$
#17926500
b1101 /
1$
#17945000
0$
#17963500
b1110 /
1$
#17982000
0$
#18000500
b1111 /
1$
#18019000
0$
#18037500
b10000 /
1$
#18056000
0$
#18074500
b10001 /
1$
#18093000
0$
#18111500
b10010 /
1$
#18130000
0$
#18148500
b10011 /
1$
#18167000
0$
#18185500
b10100 /
1$
#18204000
0$
#18222500
b10101 /
1$
#18241000
0$
#18259500
b10110 /
1$
#18278000
0$
#18296500
b10111 /
1$
#18315000
0$
#18333500
b11000 /
1$
#18352000
0$
#18370500
b11001 /
1$
#18389000
0$
#18407500
b11010 /
1$
#18426000
0$
#18444500
b11011 /
1$
#18463000
0$
#18481500
b11100 /
1$
#18500000
0$
#18518500
b11101 /
1$
#18537000
0$
#18555500
b11110 /
1$
#18574000
0$
#18592500
b11111 /
1$
#18611000
0$
#18629500
b100000 /
1$
#18648000
0$
#18666500
b100001 /
1$
#18685000
0$
#18703500
b100010 /
1$
#18722000
0$
#18740500
b100011 /
1$
#18759000
0$
#18777500
b100100 /
1$
#18796000
0$
#18814500
b100101 /
1$
#18833000
0$
