uart/receiver/uart_rx.v
// UART Reciever for Tang Nano 9k
// 27 MHz Clock --> 115200 baud rate ~ 234 CLKS_PER_BIT

module uart_rx 
    #(parameter CLKS_PER_BIT = 234)
    (
        input        i_Clock,
        input        i_Rx_Serial,
        output       o_Rx_DV,
        output [7:0] o_Rx_Byte
    );
    
    parameter s_IDLE         = 3'b000;
    parameter s_RX_START_BIT = 3'b001;
    parameter s_RX_DATA_BITS = 3'b010;
    parameter s_RX_STOP_BIT  = 3'b011;
    parameter s_CLEANUP      = 3'b100;
   
    reg           r_Rx_Data_R = 1'b1;
    reg           r_Rx_Data   = 1'b1;
    
    reg [7:0]     r_Clock_Count = 0;
    reg [2:0]     r_Bit_Index   = 0; //8 bits total
    reg [7:0]     r_Rx_Byte     = 0;
    reg           r_Rx_DV       = 0;
    reg [2:0]     r_SM_Main     = 0;

    // double register incoming data --> metastability protection   
    always @(posedge i_Clock) begin
        r_Rx_Data_R <= i_Rx_Serial;
        r_Rx_Data <= r_Rx_Data_R;
    end

    always @(posedge i_Clock) begin
        case (r_SM_Main)
            s_IDLE : begin 
                r_Rx_DV <= 1'b0;
                r_Clock_Count <= 0;
                r_Bit_Index <= 0;

                if (r_Rx_Data == 1'b0) // start bit detected
                    r_SM_Main <= s_RX_START_BIT;
                else
                    r_SM_Main <= s_IDLE;
            end

            s_RX_START_BIT : begin 
                // wait to sample at the midpoint of the bit period
                // if remains low --> valid start bit; reset counter and begin sampling
                // if is high --> noise/glitch, return to idle
                if (r_Clock_Count == ((CLKS_PER_BIT - 1)/2)) begin
                    if (r_Rx_Data == 1'b0) begin
                        r_Clock_Count <= 0; // reset counter, the middle is valid
                        r_SM_Main <= s_RX_DATA_BITS; 
                    end else begin
                        r_SM_Main <= s_IDLE; // glitch? return to idle state
                    end
                end else begin
                    r_Clock_Count <= r_Clock_Count + 1;
                    r_SM_Main <= s_RX_START_BIT;
                end
            end

            s_RX_DATA_BITS : begin
                if (r_Clock_Count < CLKS_PER_BIT - 1) begin
                    r_Clock_Count <= r_Clock_Count + 1;
                    r_SM_Main <= s_RX_DATA_BITS;
                end else begin
                    r_Clock_Count <= 0;
                    r_Rx_Byte[r_Bit_Index] <= r_Rx_Data;

                    // check if we have recieved all 8 bits, if we have, clear bit idx and go to STOP
                    if (r_Bit_Index < 7) begin
                        r_Bit_Index <= r_Bit_Index + 1;
                        r_SM_Main <= s_RX_DATA_BITS;
                    end else begin
                        r_Bit_Index <= 0;
                        r_SM_Main <= s_RX_STOP_BIT;
                    end
                end
            end

            s_RX_STOP_BIT : begin
                if (r_Clock_Count < CLKS_PER_BIT - 1) begin
                    r_Clock_Count <= r_Clock_Count + 1;
                    r_SM_Main <= s_RX_STOP_BIT;
                end else begin
                    r_Rx_DV <= 1'b1; // data transmission is possible
                    r_Clock_Count <= 0;
                    r_SM_Main <= s_CLEANUP;
                end
            end

            s_CLEANUP : begin
                // TODO: one-cycle pause back to IDLE
                r_SM_Main <= s_IDLE;
                r_Rx_DV <= 1'b0;
            end

            default : 
            r_SM_Main <= s_IDLE;
        endcase
    end

    assign o_Rx_DV = r_Rx_DV;
    assign o_Rx_Byte = r_Rx_Byte;
endmodule

uart/receiver/uart_rx_tb.v
`timescale 1ns/1ps

module uart_rx_tb;

    // Testbench uses a 27 MHz clock (Tang Nano 9K)
    // 115200 baud UART --> CLKS_PER_BIT = 234
    parameter c_CLOCK_PERIOD_NS = 37;
    parameter c_CLKS_PER_BIT    = 234;
    parameter c_BIT_PERIOD      = 234 * 37; // 8658

    reg r_Clock = 0;
    reg r_Rx_Serial = 1'b1;
    wire  o_Rx_DV; 
    wire [7:0] o_Rx_Byte;

    uart_rx #(.CLKS_PER_BIT(c_CLKS_PER_BIT)) UUR (
        .i_Clock(r_Clock),
        .i_Rx_Serial(r_Rx_Serial),
        .o_Rx_DV(o_Rx_DV),
        .o_Rx_Byte(o_Rx_Byte)
    );

    task UART_WRITE_BYTE;
        input [7:0] i_byte;
        integer k;
        begin
            
            // send start bit, wait for 1 bit period
            r_Rx_Serial <= 1'b0;
            #(c_BIT_PERIOD);

            // send data bits
            for (k = 0; k < 8; k = k + 1)
                begin
                    r_Rx_Serial <= i_byte[k];
                    #(c_BIT_PERIOD);
                end

            // send stop bit
            r_Rx_Serial <= 1'b1;
            #(c_BIT_PERIOD);    
        end
    endtask

    always begin
        #(c_CLOCK_PERIOD_NS/2) r_Clock <= !r_Clock;
    end
    /*
    always @(posedge r_Clock) begin
        $display("Time=%0t | state=%0d, r_Rx_Serial=%b, Rx_Data_R=%b, Rx_Data=%b, r_Rx_Byte=%b, o_Rx_Byte=%b",
        $time, UUR.r_SM_Main, r_Rx_Serial, UUR.r_Rx_Data_R, UUR.r_Rx_Data, UUR.r_Rx_Byte, o_Rx_Byte);
    end
    */

    always @(posedge r_Clock)begin
        $display("Time=%0t | state=%0d, internal_r_Rx_DV=%b, port_o_Rx_DV=%b",
          $time, UUR.r_SM_Main, UUR.r_Rx_DV, o_Rx_DV);
    end
    
    initial begin
        $dumpfile("uart_rx_tb.vcd");
        $dumpvars(0, uart_rx_tb);
    end

    initial begin

        // wait two clock cycles
        @(posedge r_Clock);
        @(posedge r_Clock);
        
        // race condition
        fork
            UART_WRITE_BYTE(8'hFF);
            $display("Time=%0t | task finished, about to wait for DV", $time);
            @(posedge o_Rx_DV);
        join

        if (o_Rx_Byte == 8'hFF)
            $display("Success");
        else
            $display("Failed");
        $finish;
    end

endmodule

uart/receiver/uart_rx_tb.vcd
$date
	Mon Aug 24 11:17:00 2026
$end
$version
	Icarus Verilog
$end
$timescale
	1ps
$end
$scope module uart_rx_tb $end
$var wire 1 ! o_Rx_DV $end
$var wire 8 " o_Rx_Byte [7:0] $end
$var parameter 64 # c_BIT_PERIOD $end
$var parameter 32 $ c_CLKS_PER_BIT $end
$var parameter 32 % c_CLOCK_PERIOD_NS $end
$var reg 1 & r_Clock $end
$var reg 1 ' r_Rx_Serial $end
$scope module UUR $end
$var wire 1 & i_Clock $end
$var wire 1 ' i_Rx_Serial $end
$var wire 8 ( o_Rx_Byte [7:0] $end
$var wire 1 ! o_Rx_DV $end
$var parameter 32 ) CLKS_PER_BIT $end
$var parameter 3 * s_CLEANUP $end
$var parameter 3 + s_IDLE $end
$var parameter 3 , s_RX_DATA_BITS $end
$var parameter 3 - s_RX_START_BIT $end
$var parameter 3 . s_RX_STOP_BIT $end
$var reg 3 / r_Bit_Index [2:0] $end
$var reg 8 0 r_Clock_Count [7:0] $end
$var reg 8 1 r_Rx_Byte [7:0] $end
$var reg 1 2 r_Rx_DV $end
$var reg 1 3 r_Rx_Data $end
$var reg 1 4 r_Rx_Data_R $end
$var reg 3 5 r_SM_Main [2:0] $end
$upscope $end
$scope task UART_WRITE_BYTE $end
$var reg 8 6 i_byte [7:0] $end
$var integer 32 7 k [31:0] $end
$upscope $end
$upscope $end
$enddefinitions $end
$comment Show the parameter values. $end
$dumpall
b11 .
b1 -
b10 ,
b0 +
b100 *
b11101010 )
b100101 %
b11101010 $
b10000111010010 #
$end
#0
$dumpvars
bx 7
bx 6
b0 5
14
13
02
b0 1
b0 0
b0 /
b0 (
1'
0&
b0 "
0!
$end
#18000
1&
#36000
0&
#54000
0'
b11111111 6
1&
#72000
0&
#90000
04
1&
#108000
0&
#126000
03
1&
#144000
0&
#162000
b1 5
1&
#180000
0&
#198000
b1 0
1&
#216000
0&
#234000
b10 0
1&
#252000
0&
#270000
b11 0
1&
#288000
0&
#306000
b100 0
1&
#324000
0&
#342000
b101 0
1&
#360000
0&
#378000
b110 0
1&
#396000
0&
#414000
b111 0
1&
#432000
0&
#450000
b1000 0
1&
#468000
0&
#486000
b1001 0
1&
#504000
0&
#522000
b1010 0
1&
#540000
0&
#558000
b1011 0
1&
#576000
0&
#594000
b1100 0
1&
#612000
0&
#630000
b1101 0
1&
#648000
0&
#666000
b1110 0
1&
#684000
0&
#702000
b1111 0
1&
#720000
0&
#738000
b10000 0
1&
#756000
0&
#774000
b10001 0
1&
#792000
0&
#810000
b10010 0
1&
#828000
0&
#846000
b10011 0
1&
#864000
0&
#882000
b10100 0
1&
#900000
0&
#918000
b10101 0
1&
#936000
0&
#954000
b10110 0
1&
#972000
0&
#990000
b10111 0
1&
#1008000
0&
#1026000
b11000 0
1&
#1044000
0&
#1062000
b11001 0
1&
#1080000
0&
#1098000
b11010 0
1&
#1116000
0&
#1134000
b11011 0
1&
#1152000
0&
#1170000
b11100 0
1&
#1188000
0&
#1206000
b11101 0
1&
#1224000
0&
#1242000
b11110 0
1&
#1260000
0&
#1278000
b11111 0
1&
#1296000
0&
#1314000
b100000 0
1&
#1332000
0&
#1350000
b100001 0
1&
#1368000
0&
#1386000
b100010 0
1&
#1404000
0&
#1422000
b100011 0
1&
#1440000
0&
#1458000
b100100 0
1&
#1476000
0&
#1494000
b100101 0
1&
#1512000
0&
#1530000
b100110 0
1&
#1548000
0&
#1566000
b100111 0
1&
#1584000
0&
#1602000
b101000 0
1&
#1620000
0&
#1638000
b101001 0
1&
#1656000
0&
#1674000
b101010 0
1&
#1692000
0&
#1710000
b101011 0
1&
#1728000
0&
#1746000
b101100 0
1&
#1764000
0&
#1782000
b101101 0
1&
#1800000
0&
#1818000
b101110 0
1&
#1836000
0&
#1854000
b101111 0
1&
#1872000
0&
#1890000
b110000 0
1&
#1908000
0&
#1926000
b110001 0
1&
#1944000
0&
#1962000
b110010 0
1&
#1980000
0&
#1998000
b110011 0
1&
#2016000
0&
#2034000
b110100 0
1&
#2052000
0&
#2070000
b110101 0
1&
#2088000
0&
#2106000
b110110 0
1&
#2124000
0&
#2142000
b110111 0
1&
#2160000
0&
#2178000
b111000 0
1&
#2196000
0&
#2214000
b111001 0
1&
#2232000
0&
#2250000
b111010 0
1&
#2268000
0&
#2286000
b111011 0
1&
#2304000
0&
#2322000
b111100 0
1&
#2340000
0&
#2358000
b111101 0
1&
#2376000
0&
#2394000
b111110 0
1&
#2412000
0&
#2430000
b111111 0
1&
#2448000
0&
#2466000
b1000000 0
1&
#2484000
0&
#2502000
b1000001 0
1&
#2520000
0&
#2538000
b1000010 0
1&
#2556000
0&
#2574000
b1000011 0
1&
#2592000
0&
#2610000
b1000100 0
1&
#2628000
0&
#2646000
b1000101 0
1&
#2664000
0&
#2682000
b1000110 0
1&
#2700000
0&
#2718000
b1000111 0
1&
#2736000
0&
#2754000
b1001000 0
1&
#2772000
0&
#2790000
b1001001 0
1&
#2808000
0&
#2826000
b1001010 0
1&
#2844000
0&
#2862000
b1001011 0
1&
#2880000
0&
#2898000
b1001100 0
1&
#2916000
0&
#2934000
b1001101 0
1&
#2952000
0&
#2970000
b1001110 0
1&
#2988000
0&
#3006000
b1001111 0
1&
#3024000
0&
#3042000
b1010000 0
1&
#3060000
0&
#3078000
b1010001 0
1&
#3096000
0&
#3114000
b1010010 0
1&
#3132000
0&
#3150000
b1010011 0
1&
#3168000
0&
#3186000
b1010100 0
1&
#3204000
0&
#3222000
b1010101 0
1&
#3240000
0&
#3258000
b1010110 0
1&
#3276000
0&
#3294000
b1010111 0
1&
#3312000
0&
#3330000
b1011000 0
1&
#3348000
0&
#3366000
b1011001 0
1&
#3384000
0&
#3402000
b1011010 0
1&
#3420000
0&
#3438000
b1011011 0
1&
#3456000
0&
#3474000
b1011100 0
1&
#3492000
0&
#3510000
b1011101 0
1&
#3528000
0&
#3546000
b1011110 0
1&
#3564000
0&
#3582000
b1011111 0
1&
#3600000
0&
#3618000
b1100000 0
1&
#3636000
0&
#3654000
b1100001 0
1&
#3672000
0&
#3690000
b1100010 0
1&
#3708000
0&
#3726000
b1100011 0
1&
#3744000
0&
#3762000
b1100100 0
1&
#3780000
0&
#3798000
b1100101 0
1&
#3816000
0&
#3834000
b1100110 0
1&
#3852000
0&
#3870000
b1100111 0
1&
#3888000
0&
#3906000
b1101000 0
1&
#3924000
0&
#3942000
b1101001 0
1&
#3960000
0&
#3978000
b1101010 0
1&
#3996000
0&
#4014000
b1101011 0
1&
#4032000
0&
#4050000
b1101100 0
1&
#4068000
0&
#4086000
b1101101 0
1&
#4104000
0&
#4122000
b1101110 0
1&
#4140000
0&
#4158000
b1101111 0
1&
#4176000
0&
#4194000
b1110000 0
1&
#4212000
0&
#4230000
b1110001 0
1&
#4248000
0&
#4266000
b1110010 0
1&
#4284000
0&
#4302000
b1110011 0
1&
#4320000
0&
#4338000
b1110100 0
1&
#4356000
0&
#4374000
b10 5
b0 0
1&
#4392000
0&
#4410000
b1 0
1&
#4428000
0&
#4446000
b10 0
1&
#4464000
0&
#4482000
b11 0
1&
#4500000
0&
#4518000
b100 0
1&
#4536000
0&
#4554000
b101 0
1&
#4572000
0&
#4590000
b110 0
1&
#4608000
0&
#4626000
b111 0
1&
#4644000
0&
#4662000
b1000 0
1&
#4680000
0&
#4698000
b1001 0
1&
#4716000
0&
#4734000
b1010 0
1&
#4752000
0&
#4770000
b1011 0
1&
#4788000
0&
#4806000
b1100 0
1&
#4824000
0&
#4842000
b1101 0
1&
#4860000
0&
#4878000
b1110 0
1&
#4896000
0&
#4914000
b1111 0
1&
#4932000
0&
#4950000
b10000 0
1&
#4968000
0&
#4986000
b10001 0
1&
#5004000
0&
#5022000
b10010 0
1&
#5040000
0&
#5058000
b10011 0
1&
#5076000
0&
#5094000
b10100 0
1&
#5112000
0&
#5130000
b10101 0
1&
#5148000
0&
#5166000
b10110 0
1&
#5184000
0&
#5202000
b10111 0
1&
#5220000
0&
#5238000
b11000 0
1&
#5256000
0&
#5274000
b11001 0
1&
#5292000
0&
#5310000
b11010 0
1&
#5328000
0&
#5346000
b11011 0
1&
#5364000
0&
#5382000
b11100 0
1&
#5400000
0&
#5418000
b11101 0
1&
#5436000
0&
#5454000
b11110 0
1&
#5472000
0&
#5490000
b11111 0
1&
#5508000
0&
#5526000
b100000 0
1&
#5544000
0&
#5562000
b100001 0
1&
#5580000
0&
#5598000
b100010 0
1&
#5616000
0&
#5634000
b100011 0
1&
#5652000
0&
#5670000
b100100 0
1&
#5688000
0&
#5706000
b100101 0
1&
#5724000
0&
#5742000
b100110 0
1&
#5760000
0&
#5778000
b100111 0
1&
#5796000
0&
#5814000
b101000 0
1&
#5832000
0&
#5850000
b101001 0
1&
#5868000
0&
#5886000
b101010 0
1&
#5904000
0&
#5922000
b101011 0
1&
#5940000
0&
#5958000
b101100 0
1&
#5976000
0&
#5994000
b101101 0
1&
#6012000
0&
#6030000
b101110 0
1&
#6048000
0&
#6066000
b101111 0
1&
#6084000
0&
#6102000
b110000 0
1&
#6120000
0&
#6138000
b110001 0
1&
#6156000
0&
#6174000
b110010 0
1&
#6192000
0&
#6210000
b110011 0
1&
#6228000
0&
#6246000
b110100 0
1&
#6264000
0&
#6282000
b110101 0
1&
#6300000
0&
#6318000
b110110 0
1&
#6336000
0&
#6354000
b110111 0
1&
#6372000
0&
#6390000
b111000 0
1&
#6408000
0&
#6426000
b111001 0
1&
#6444000
0&
#6462000
b111010 0
1&
#6480000
0&
#6498000
b111011 0
1&
#6516000
0&
#6534000
b111100 0
1&
#6552000
0&
#6570000
b111101 0
1&
#6588000
0&
#6606000
b111110 0
1&
#6624000
0&
#6642000
b111111 0
1&
#6660000
0&
#6678000
b1000000 0
1&
#6696000
0&
#6714000
b1000001 0
1&
#6732000
0&
#6750000
b1000010 0
1&
#6768000
0&
#6786000
b1000011 0
1&
#6804000
0&
#6822000
b1000100 0
1&
#6840000
0&
#6858000
b1000101 0
1&
#6876000
0&
#6894000
b1000110 0
1&
#6912000
0&
#6930000
b1000111 0
1&
#6948000
0&
#6966000
b1001000 0
1&
#6984000
0&
#7002000
b1001001 0
1&
#7020000
0&
#7038000
b1001010 0
1&
#7056000
0&
#7074000
b1001011 0
1&
#7092000
0&
#7110000
b1001100 0
1&
#7128000
0&
#7146000
b1001101 0
1&
#7164000
0&
#7182000
b1001110 0
1&
#7200000
0&
#7218000
b1001111 0
1&
#7236000
0&
#7254000
b1010000 0
1&
#7272000
0&
#7290000
b1010001 0
1&
#7308000
0&
#7326000
b1010010 0
1&
#7344000
0&
#7362000
b1010011 0
1&
#7380000
0&
#7398000
b1010100 0
1&
#7416000
0&
#7434000
b1010101 0
1&
#7452000
0&
#7470000
b1010110 0
1&
#7488000
0&
#7506000
b1010111 0
1&
#7524000
0&
#7542000
b1011000 0
1&
#7560000
0&
#7578000
b1011001 0
1&
#7596000
0&
#7614000
b1011010 0
1&
#7632000
0&
#7650000
b1011011 0
1&
#7668000
0&
#7686000
b1011100 0
1&
#7704000
0&
#7722000
b1011101 0
1&
#7740000
0&
#7758000
b1011110 0
1&
#7776000
0&
#7794000
b1011111 0
1&
#7812000
0&
#7830000
b1100000 0
1&
#7848000
0&
#7866000
b1100001 0
1&
#7884000
0&
#7902000
b1100010 0
1&
#7920000
0&
#7938000
b1100011 0
1&
#7956000
0&
#7974000
b1100100 0
1&
#7992000
0&
#8010000
b1100101 0
1&
#8028000
0&
#8046000
b1100110 0
1&
#8064000
0&
#8082000
b1100111 0
1&
#8100000
0&
#8118000
b1101000 0
1&
#8136000
0&
#8154000
b1101001 0
1&
#8172000
0&
#8190000
b1101010 0
1&
#8208000
0&
#8226000
b1101011 0
1&
#8244000
0&
#8262000
b1101100 0
1&
#8280000
0&
#8298000
b1101101 0
1&
#8316000
0&
#8334000
b1101110 0
1&
#8352000
0&
#8370000
b1101111 0
1&
#8388000
0&
#8406000
b1110000 0
1&
#8424000
0&
#8442000
b1110001 0
1&
#8460000
0&
#8478000
b1110010 0
1&
#8496000
0&
#8514000
b1110011 0
1&
#8532000
0&
#8550000
b1110100 0
1&
#8568000
0&
#8586000
b1110101 0
1&
#8604000
0&
#8622000
b1110110 0
1&
#8640000
0&
#8658000
b1110111 0
1&
#8676000
0&
#8694000
b1111000 0
1&
#8712000
0&
1'
b0 7
#8730000
14
b1111001 0
1&
#8748000
0&
#8766000
b1111010 0
13
1&
#8784000
0&
#8802000
b1111011 0
1&
#8820000
0&
#8838000
b1111100 0
1&
#8856000
0&
#8874000
b1111101 0
1&
#8892000
0&
#8910000
b1111110 0
1&
#8928000
0&
#8946000
b1111111 0
1&
#8964000
0&
#8982000
b10000000 0
1&
#9000000
0&
#9018000
b10000001 0
1&
#9036000
0&
#9054000
b10000010 0
1&
#9072000
0&
#9090000
b10000011 0
1&
#9108000
0&
#9126000
b10000100 0
1&
#9144000
0&
#9162000
b10000101 0
1&
#9180000
0&
#9198000
b10000110 0
1&
#9216000
0&
#9234000
b10000111 0
1&
#9252000
0&
#9270000
b10001000 0
1&
#9288000
0&
#9306000
b10001001 0
1&
#9324000
0&
#9342000
b10001010 0
1&
#9360000
0&
#9378000
b10001011 0
1&
#9396000
0&
#9414000
b10001100 0
1&
#9432000
0&
#9450000
b10001101 0
1&
#9468000
0&
#9486000
b10001110 0
1&
#9504000
0&
#9522000
b10001111 0
1&
#9540000
0&
#9558000
b10010000 0
1&
#9576000
0&
#9594000
b10010001 0
1&
#9612000
0&
#9630000
b10010010 0
1&
#9648000
0&
#9666000
b10010011 0
1&
#9684000
0&
#9702000
b10010100 0
1&
#9720000
0&
#9738000
b10010101 0
1&
#9756000
0&
#9774000
b10010110 0
1&
#9792000
0&
#9810000
b10010111 0
1&
#9828000
0&
#9846000
b10011000 0
1&
#9864000
0&
#9882000
b10011001 0
1&
#9900000
0&
#9918000
b10011010 0
1&
#9936000
0&
#9954000
b10011011 0
1&
#9972000
0&
#9990000
b10011100 0
1&
#10008000
0&
#10026000
b10011101 0
1&
#10044000
0&
#10062000
b10011110 0
1&
#10080000
0&
#10098000
b10011111 0
1&
#10116000
0&
#10134000
b10100000 0
1&
#10152000
0&
#10170000
b10100001 0
1&
#10188000
0&
#10206000
b10100010 0
1&
#10224000
0&
#10242000
b10100011 0
1&
#10260000
0&
#10278000
b10100100 0
1&
#10296000
0&
#10314000
b10100101 0
1&
#10332000
0&
#10350000
b10100110 0
1&
#10368000
0&
#10386000
b10100111 0
1&
#10404000
0&
#10422000
b10101000 0
1&
#10440000
0&
#10458000
b10101001 0
1&
#10476000
0&
#10494000
b10101010 0
1&
#10512000
0&
#10530000
b10101011 0
1&
#10548000
0&
#10566000
b10101100 0
1&
#10584000
0&
#10602000
b10101101 0
1&
#10620000
0&
#10638000
b10101110 0
1&
#10656000
0&
#10674000
b10101111 0
1&
#10692000
0&
#10710000
b10110000 0
1&
#10728000
0&
#10746000
b10110001 0
1&
#10764000
0&
#10782000
b10110010 0
1&
#10800000
0&
#10818000
b10110011 0
1&
#10836000
0&
#10854000
b10110100 0
1&
#10872000
0&
#10890000
b10110101 0
1&
#10908000
0&
#10926000
b10110110 0
1&
#10944000
0&
#10962000
b10110111 0
1&
#10980000
0&
#10998000
b10111000 0
1&
#11016000
0&
#11034000
b10111001 0
1&
#11052000
0&
#11070000
b10111010 0
1&
#11088000
0&
#11106000
b10111011 0
1&
#11124000
0&
#11142000
b10111100 0
1&
#11160000
0&
#11178000
b10111101 0
1&
#11196000
0&
#11214000
b10111110 0
1&
#11232000
0&
#11250000
b10111111 0
1&
#11268000
0&
#11286000
b11000000 0
1&
#11304000
0&
#11322000
b11000001 0
1&
#11340000
0&
#11358000
b11000010 0
1&
#11376000
0&
#11394000
b11000011 0
1&
#11412000
0&
#11430000
b11000100 0
1&
#11448000
0&
#11466000
b11000101 0
1&
#11484000
0&
#11502000
b11000110 0
1&
#11520000
0&
#11538000
b11000111 0
1&
#11556000
0&
#11574000
b11001000 0
1&
#11592000
0&
#11610000
b11001001 0
1&
#11628000
0&
#11646000
b11001010 0
1&
#11664000
0&
#11682000
b11001011 0
1&
#11700000
0&
#11718000
b11001100 0
1&
#11736000
0&
#11754000
b11001101 0
1&
#11772000
0&
#11790000
b11001110 0
1&
#11808000
0&
#11826000
b11001111 0
1&
#11844000
0&
#11862000
b11010000 0
1&
#11880000
0&
#11898000
b11010001 0
1&
#11916000
0&
#11934000
b11010010 0
1&
#11952000
0&
#11970000
b11010011 0
1&
#11988000
0&
#12006000
b11010100 0
1&
#12024000
0&
#12042000
b11010101 0
1&
#12060000
0&
#12078000
b11010110 0
1&
#12096000
0&
#12114000
b11010111 0
1&
#12132000
0&
#12150000
b11011000 0
1&
#12168000
0&
#12186000
b11011001 0
1&
#12204000
0&
#12222000
b11011010 0
1&
#12240000
0&
#12258000
b11011011 0
1&
#12276000
0&
#12294000
b11011100 0
1&
#12312000
0&
#12330000
b11011101 0
1&
#12348000
0&
#12366000
b11011110 0
1&
#12384000
0&
#12402000
b11011111 0
1&
#12420000
0&
#12438000
b11100000 0
1&
#12456000
0&
#12474000
b11100001 0
1&
#12492000
0&
#12510000
b11100010 0
1&
#12528000
0&
#12546000
b11100011 0
1&
#12564000
0&
#12582000
b11100100 0
1&
#12600000
0&
#12618000
b11100101 0
1&
#12636000
0&
#12654000
b11100110 0
1&
#12672000
0&
#12690000
b11100111 0
1&
#12708000
0&
#12726000
b11101000 0
1&
#12744000
0&
#12762000
b11101001 0
1&
#12780000
0&
#12798000
b1 /
b1 "
b1 (
b1 1
b0 0
1&
#12816000
0&
#12834000
b1 0
1&
#12852000
0&
#12870000
b10 0
1&
#12888000
0&
#12906000
b11 0
1&
#12924000
0&
#12942000
b100 0
1&
#12960000
0&
#12978000
b101 0
1&
#12996000
0&
#13014000
b110 0
1&
#13032000
0&
#13050000
b111 0
1&
#13068000
0&
#13086000
b1000 0
1&
#13104000
0&
#13122000
b1001 0
1&
#13140000
0&
#13158000
b1010 0
1&
#13176000
0&
#13194000
b1011 0
1&
#13212000
0&
#13230000
b1100 0
1&
#13248000
0&
#13266000
b1101 0
1&
#13284000
0&
#13302000
b1110 0
1&
#13320000
0&
#13338000
b1111 0
1&
#13356000
0&
#13374000
b10000 0
1&
#13392000
0&
#13410000
b10001 0
1&
#13428000
0&
#13446000
b10010 0
1&
#13464000
0&
#13482000
b10011 0
1&
#13500000
0&
#13518000
b10100 0
1&
#13536000
0&
#13554000
b10101 0
1&
#13572000
0&
#13590000
b10110 0
1&
#13608000
0&
#13626000
b10111 0
1&
#13644000
0&
#13662000
b11000 0
1&
#13680000
0&
#13698000
b11001 0
1&
#13716000
0&
#13734000
b11010 0
1&
#13752000
0&
#13770000
b11011 0
1&
#13788000
0&
#13806000
b11100 0
1&
#13824000
0&
#13842000
b11101 0
1&
#13860000
0&
#13878000
b11110 0
1&
#13896000
0&
#13914000
b11111 0
1&
#13932000
0&
#13950000
b100000 0
1&
#13968000
0&
#13986000
b100001 0
1&
#14004000
0&
#14022000
b100010 0
1&
#14040000
0&
#14058000
b100011 0
1&
#14076000
0&
#14094000
b100100 0
1&
#14112000
0&
#14130000
b100101 0
1&
#14148000
0&
#14166000
b100110 0
1&
#14184000
0&
#14202000
b100111 0
1&
#14220000
0&
#14238000
b101000 0
1&
#14256000
0&
#14274000
b101001 0
1&
#14292000
0&
#14310000
b101010 0
1&
#14328000
0&
#14346000
b101011 0
1&
#14364000
0&
#14382000
b101100 0
1&
#14400000
0&
#14418000
b101101 0
1&
#14436000
0&
#14454000
b101110 0
1&
#14472000
0&
#14490000
b101111 0
1&
#14508000
0&
#14526000
b110000 0
1&
#14544000
0&
#14562000
b110001 0
1&
#14580000
0&
#14598000
b110010 0
1&
#14616000
0&
#14634000
b110011 0
1&
#14652000
0&
#14670000
b110100 0
1&
#14688000
0&
#14706000
b110101 0
1&
#14724000
0&
#14742000
b110110 0
1&
#14760000
0&
#14778000
b110111 0
1&
#14796000
0&
#14814000
b111000 0
1&
#14832000
0&
#14850000
b111001 0
1&
#14868000
0&
#14886000
b111010 0
1&
#14904000
0&
#14922000
b111011 0
1&
#14940000
0&
#14958000
b111100 0
1&
#14976000
0&
#14994000
b111101 0
1&
#15012000
0&
#15030000
b111110 0
1&
#15048000
0&
#15066000
b111111 0
1&
#15084000
0&
#15102000
b1000000 0
1&
#15120000
0&
#15138000
b1000001 0
1&
#15156000
0&
#15174000
b1000010 0
1&
#15192000
0&
#15210000
b1000011 0
1&
#15228000
0&
#15246000
b1000100 0
1&
#15264000
0&
#15282000
b1000101 0
1&
#15300000
0&
#15318000
b1000110 0
1&
#15336000
0&
#15354000
b1000111 0
1&
#15372000
0&
#15390000
b1001000 0
1&
#15408000
0&
#15426000
b1001001 0
1&
#15444000
0&
#15462000
b1001010 0
1&
#15480000
0&
#15498000
b1001011 0
1&
#15516000
0&
#15534000
b1001100 0
1&
#15552000
0&
#15570000
b1001101 0
1&
#15588000
0&
#15606000
b1001110 0
1&
#15624000
0&
#15642000
b1001111 0
1&
#15660000
0&
#15678000
b1010000 0
1&
#15696000
0&
#15714000
b1010001 0
1&
#15732000
0&
#15750000
b1010010 0
1&
#15768000
0&
#15786000
b1010011 0
1&
#15804000
0&
#15822000
b1010100 0
1&
#15840000
0&
#15858000
b1010101 0
1&
#15876000
0&
#15894000
b1010110 0
1&
#15912000
0&
#15930000
b1010111 0
1&
#15948000
0&
#15966000
b1011000 0
1&
#15984000
0&
#16002000
b1011001 0
1&
#16020000
0&
#16038000
b1011010 0
1&
#16056000
0&
#16074000
b1011011 0
1&
#16092000
0&
#16110000
b1011100 0
1&
#16128000
0&
#16146000
b1011101 0
1&
#16164000
0&
#16182000
b1011110 0
1&
#16200000
0&
#16218000
b1011111 0
1&
#16236000
0&
#16254000
b1100000 0
1&
#16272000
0&
#16290000
b1100001 0
1&
#16308000
0&
#16326000
b1100010 0
1&
#16344000
0&
#16362000
b1100011 0
1&
#16380000
0&
#16398000
b1100100 0
1&
#16416000
0&
#16434000
b1100101 0
1&
#16452000
0&
#16470000
b1100110 0
1&
#16488000
0&
#16506000
b1100111 0
1&
#16524000
0&
#16542000
b1101000 0
1&
#16560000
0&
#16578000
b1101001 0
1&
#16596000
0&
#16614000
b1101010 0
1&
#16632000
0&
#16650000
b1101011 0
1&
#16668000
0&
#16686000
b1101100 0
1&
#16704000
0&
#16722000
b1101101 0
1&
#16740000
0&
#16758000
b1101110 0
1&
#16776000
0&
#16794000
b1101111 0
1&
#16812000
0&
#16830000
b1110000 0
1&
#16848000
0&
#16866000
b1110001 0
1&
#16884000
0&
#16902000
b1110010 0
1&
#16920000
0&
#16938000
b1110011 0
1&
#16956000
0&
#16974000
b1110100 0
1&
#16992000
0&
#17010000
b1110101 0
1&
#17028000
0&
#17046000
b1110110 0
1&
#17064000
0&
#17082000
b1110111 0
1&
#17100000
0&
#17118000
b1111000 0
1&
#17136000
0&
#17154000
b1111001 0
1&
#17172000
0&
#17190000
b1111010 0
1&
#17208000
0&
#17226000
b1111011 0
1&
#17244000
0&
#17262000
b1111100 0
1&
#17280000
0&
#17298000
b1111101 0
1&
#17316000
0&
#17334000
b1111110 0
1&
#17352000
0&
#17370000
b1111111 0
1&
b1 7
#17388000
0&
#17406000
b10000000 0
1&
#17424000
0&
#17442000
b10000001 0
1&
#17460000
0&
#17478000
b10000010 0
1&
#17496000
0&
#17514000
b10000011 0
1&
#17532000
0&
#17550000
b10000100 0
1&
#17568000
0&
#17586000
b10000101 0
1&
#17604000
0&
#17622000
b10000110 0
1&
#17640000
0&
#17658000
b10000111 0
1&
#17676000
0&
#17694000
b10001000 0
1&
#17712000
0&
#17730000
b10001001 0
1&
#17748000
0&
#17766000
b10001010 0
1&
#17784000
0&
#17802000
b10001011 0
1&
#17820000
0&
#17838000
b10001100 0
1&
#17856000
0&
#17874000
b10001101 0
1&
#17892000
0&
#17910000
b10001110 0
1&
#17928000
0&
#17946000
b10001111 0
1&
#17964000
0&
#17982000
b10010000 0
1&
#18000000
0&
#18018000
b10010001 0
1&
#18036000
0&
#18054000
b10010010 0
1&
#18072000
0&
#18090000
b10010011 0
1&
#18108000
0&
#18126000
b10010100 0
1&
#18144000
0&
#18162000
b10010101 0
1&
