uart/receiver/uart_rx.v
// UART Reciever for Tang Nano 9k
// 27 MHz Clock --> 115200 baud rate ~ 234 CLKS_PER_BIT

module uart_rx 
    #(parameter CLKS_PER_BIT = 234)
    (
        input        i_Clock,
        input        i_Rx_Serial,
        output       o_Rx_DV,
        output [7:0] o_Rx_Byte
    );
    
    parameter s_IDLE         = 3'b000;
    parameter s_RX_START_BIT = 3'b001;
    parameter s_RX_DATA_BITS = 3'b010;
    parameter s_RX_STOP_BIT  = 3'b011;
    parameter s_CLEANUP      = 3'b100;
   
    reg           r_Rx_Data_R = 1'b1;
    reg           r_Rx_Data   = 1'b1;
    
    reg [7:0]     r_Clock_Count = 0;
    reg [2:0]     r_Bit_Index   = 0; //8 bits total
    reg [7:0]     r_Rx_Byte     = 0;
    reg           r_Rx_DV       = 0;
    reg [2:0]     r_SM_Main     = 0;

    // double register incoming data --> metastability protection   
    always @(posedge i_Clock) begin
        r_Rx_Data_R <= i_Rx_Serial;
        r_Rx_Data <= r_Rx_Data_R;
    end

    always @(posedge i_Clock) begin
        case (r_SM_Main)
            s_IDLE : begin 
                r_Rx_DV <= 1'b0;
                r_Clock_Count <= 0;
                r_Bit_Index <= 0;

                if (r_Rx_Data == 1'b0) // start bit detected
                    r_SM_Main <= s_RX_START_BIT;
                else
                    r_SM_Main <= s_IDLE;
            end

            s_RX_START_BIT : begin 
                // wait to sample at the midpoint of the bit period
                // if remains low --> valid start bit; reset counter and begin sampling
                // if is high --> noise/glitch, return to idle
                if (r_Clock_Count == ((CLKS_PER_BIT - 1)/2)) begin
                    if (r_Rx_Data == 1'b0) begin
                        r_Clock_Count <= 0; // reset counter, the middle is valid
                        r_SM_Main <= s_RX_DATA_BITS; 
                    end else begin
                        r_SM_Main <= s_IDLE; // glitch? return to idle state
                    end
                end else begin
                    r_Clock_Count <= r_Clock_Count + 1;
                    r_SM_Main <= s_RX_START_BIT;
                end
            end

            s_RX_DATA_BITS : begin
                if (r_Clock_Count < CLKS_PER_BIT - 1) begin
                    r_Clock_Count <= r_Clock_Count + 1;
                    r_SM_Main <= s_RX_DATA_BITS;
                end else begin
                    r_Clock_Count <= 0;
                    r_Rx_Byte[r_Bit_Index] <= r_Rx_Data;

                    // check if we have recieved all 8 bits, if we have, clear bit idx and go to STOP
                    if (r_Bit_Index < 7) begin
                        r_Bit_Index <= r_Bit_Index + 1;
                        r_SM_Main <= s_RX_DATA_BITS;
                    end else begin
                        r_Bit_Index <= 0;
                        r_SM_Main <= s_RX_STOP_BIT;
                    end
                end
            end

            s_RX_STOP_BIT : begin
                if (r_Clock_Count < CLKS_PER_BIT - 1) begin
                    r_Clock_Count <= r_Clock_Count + 1;
                    r_SM_Main <= s_RX_STOP_BIT;
                end else begin
                    r_Rx_DV <= 1'b1; // data transmission is possible
                    r_Clock_Count <= 0;
                    r_SM_Main <= s_CLEANUP;
                end
            end

            s_CLEANUP : begin
                // TODO: one-cycle pause back to IDLE
                r_SM_Main <= s_IDLE;
                r_Rx_DV <= 1'b0;
            end

            default : 
            r_SM_Main <= s_IDLE;
        endcase
    end

    assign o_Rx_DV = r_Rx_DV;
    assign o_Rx_Byte = r_Rx_Byte;
endmodule

uart/transmitter/uart_tx.v
// UART Transmitter for Tang Nano 9k
// 27 MHz Clock --> 115200 baud rate; ~234 CLKS_PER_BIT
module uart_tx
    #(parameter CLKS_PER_BIT = 234)

    (
      input i_Clock,
      input i_Tx_DV, // data valid (answer from driving line high)
      input [7:0] i_Tx_Byte,
      output o_Tx_Active,
      output reg o_Tx_Serial,
      output o_Tx_Done
    );

    parameter s_IDLE            = 3'b000;
    parameter s_TX_START_BIT    = 3'b001;
    parameter s_TX_DATA_BITS    = 3'b010;
    parameter s_TX_STOP_BIT     = 3'b011;
    parameter s_CLEANUP         = 3'b100;

    reg [2:0] r_SM_Main     = 0; // holds current state of UART transmiotter
    reg [7:0] r_Clock_Count = 0; // holds clock cycles within the current bit period
    reg [2:0] r_Bit_Index   = 0; // which one of the 8 data bits is being transmitted
    reg [7:0] r_Tx_Data     = 0; // copy of i_Tx_Byte --> prevents corruption of i_Tx_byte
    reg r_Tx_Done           = 0; // flag --> finished sending byte
    reg r_Tx_Active         = 0; // flag --> high during transmission, low du ring idle

    always @(posedge i_Clock) begin
    case (r_SM_Main)
      s_IDLE: begin
        // TODO: what should the line do while idle?
        o_Tx_Serial <= 1'b1; // drive the line high while idle
        r_Tx_Done   <= 1'b0; // reset; byte transmission ready to begin
        r_Clock_Count <= 0; // reset the clock count
        r_Bit_Index <= 0; // reset the bit index

        // TODO: what should happen when i_Tx_DV pulses?
        if (i_Tx_DV == 1'b1) begin
            r_Tx_Active <= 1'b1; // show line is active
            r_Tx_Data <= i_Tx_Byte; // data to send is i_Tx_Byte;
            r_SM_Main <= s_TX_START_BIT; // set state to (START_BIT)
        end
      end

      s_TX_START_BIT: begin
        // TODO: drive the line low, count one bit period
        o_Tx_Serial <= 1'b0; //drive the line low

        // wait for one bit period before sending data 
        if (r_Clock_Count < CLKS_PER_BIT-1) begin
            r_Clock_Count <= r_Clock_Count + 1;
            r_SM_Main <= s_TX_START_BIT; // remain in s_TX_START_BIT
        end else begin
            r_Clock_Count <= 0;
            r_SM_Main <= s_TX_DATA_BITS;
        end
      end

      s_TX_DATA_BITS: begin
        // TODO: shift r_Tx_Data out one bit at a time
        o_Tx_Serial <= r_Tx_Data[r_Bit_Index];

        if (r_Clock_Count < CLKS_PER_BIT-1) begin
            r_Clock_Count <= r_Clock_Count + 1;
            r_SM_Main <= s_TX_DATA_BITS;
        end else begin
            r_Clock_Count <= 0;

            // Check if we have sent all bits in a data packet
            if (r_Bit_Index < 7) begin
                r_Bit_Index <= r_Bit_Index + 1;
                r_SM_Main <= s_TX_DATA_BITS;
            end else begin 
                // all data bits sent out; reset r_BIT, and transition to next state
                r_Bit_Index <= 0;
                r_SM_Main <= s_TX_STOP_BIT;
            end
        end
      end

      s_TX_STOP_BIT: begin
        // TODO: drive line high, count one bit period, signal done
        o_Tx_Serial <= 1;
        
        if (r_Clock_Count < CLKS_PER_BIT-1) begin
            r_Clock_Count <= r_Clock_Count + 1;
            r_SM_Main <= s_TX_STOP_BIT;
        end else begin 
            r_Tx_Done <= 1'b1;
            r_Clock_Count <= 0;
            r_SM_Main <= s_CLEANUP;
            r_Tx_Active <= 1'b0;
        end
      end

      s_CLEANUP: begin
        // TODO: one-cycle pause back to IDLE
        r_Tx_Done <= 1'b1;
        r_SM_Main <= s_IDLE;
      end

      default: r_SM_Main <= s_IDLE;
    endcase
  end

  assign o_Tx_Active = r_Tx_Active;
  assign o_Tx_Done   = r_Tx_Done;

endmodule

uart/echo/uart_top.v
module uart_top
    #(parameter CLKS_PER_BIT = 234)
    (
        input i_Clock,
        input i_Rx_Serial,
        output o_Tx_Serial
    );

    wire    w_Rx_DV;
    wire [7:0] w_Rx_Byte;
    wire    w_Tx_Active;
    wire    w_Tx_Done;

    uart_rx #(.CLKS_PER_BIT(CLKS_PER_BIT)) UART_RX_INST
        (
            .i_Clock(i_Clock),
            .i_Rx_Serial(i_Rx_Serial),
            .o_Rx_DV(w_Rx_DV),
            .o_Rx_Byte(w_Rx_Byte)
        );

    uart_tx #(.CLKS_PER_BIT(CLKS_PER_BIT)) UART_TX_INST
        (
            .i_Clock(i_Clock),
            .i_Tx_DV(w_Rx_DV),
            .i_Tx_Byte(w_Rx_Byte),
            .o_Tx_Active(w_Tx_Active),
            .o_Tx_Serial(o_Tx_Serial),
            .o_Tx_Done(w_Tx_Done)
        );

endmodule

uart/echo/uart_echo_tb.v
`timescale 1ns/10ps

module uart_echo_tb;
    // Testbench uses a 27 MHz clock (Tang Nano 9K)
    // 115200 baud UART --> CLKS_PER_BIT = 234
    parameter c_CLOCK_PERIOD_NS = 37;
    parameter c_CLKS_PER_BIT    = 234;
    parameter c_BIT_PERIOD      = 234 * 37; // 8658

    reg  r_Clock = 0;
    reg  r_Rx_Serial = 1; // initial state
    wire w_Tx_Serial;

    wire w_Checked_DV; 
    wire [7:0] w_Checked_Byte;

    reg [7:0] r_Sent_Byte;

    uart_top #(.CLKS_PER_BIT(c_CLKS_PER_BIT)) UUT
        (
            .i_Clock(r_Clock),
            .i_Rx_Serial(r_Rx_Serial),
            .o_Tx_Serial(w_Tx_Serial)
        );
    
    uart_rx #(.CLKS_PER_BIT(c_CLKS_PER_BIT)) CHECKER
        (
            .i_Clock(r_Clock),
            .i_Rx_Serial(w_Tx_Serial),
            .o_Rx_DV(w_Checked_DV),
            .o_Rx_Byte(w_Checked_Byte)
        );

    always 
        #(c_CLOCK_PERIOD_NS/2) r_Clock <= !r_Clock;
    
    // Takes in input byte and serializes it
    task UART_WRITE_BYTE;
        input [7:0] i_Data;
        integer     ii;
        begin

        // Send Start Bit
        r_Rx_Serial <= 1'b0;
        #(c_BIT_PERIOD);

        // Send Data Byte
        for (ii=0; ii<8; ii=ii+1)
            begin
            r_Rx_Serial <= i_Data[ii];
            #(c_BIT_PERIOD);
            end

        // Send Stop Bit
        r_Rx_Serial <= 1'b1;
        #(c_BIT_PERIOD);
        end
    endtask // UART_WRITE_BYTE

    // Waveform dump for GTKWave
    initial begin
        $dumpfile("uart_echo_tb.vcd");
        $dumpvars(0, uart_echo_tb);
    end

    initial
        begin
        // wait for signal to settle
        @(posedge r_Clock);
        
        // save byte state for reference
        r_Sent_Byte <= 8'hFF;

        @(posedge r_Clock);
        UART_WRITE_BYTE(r_Sent_Byte);
        
        @(posedge w_Checked_DV);

        if (w_Checked_Byte == r_Sent_Byte)
            $display("Test Passed - Correct Byte Received");
        else
            $display("Test Failed - Incorrect Byte Received");

      $finish;
    end
endmodule

uart/echo/uart_echo_tb.vcd
$date
	Mon Aug 24 01:02:26 2026
$end
$version
	Icarus Verilog
$end
$timescale
	10ps
$end
$scope module uart_echo_tb $end
$var wire 1 ! w_Tx_Serial $end
$var wire 1 " w_Checked_DV $end
$var wire 8 # w_Checked_Byte [7:0] $end
$var parameter 64 $ c_BIT_PERIOD $end
$var parameter 32 % c_CLKS_PER_BIT $end
$var parameter 32 & c_CLOCK_PERIOD_NS $end
$var reg 1 ' r_Clock $end
$var reg 1 ( r_Rx_Serial $end
$var reg 8 ) r_Sent_Byte [7:0] $end
$scope module CHECKER $end
$var wire 1 ' i_Clock $end
$var wire 8 * o_Rx_Byte [7:0] $end
$var wire 1 " o_Rx_DV $end
$var wire 1 ! i_Rx_Serial $end
$var parameter 32 + CLKS_PER_BIT $end
$var parameter 3 , s_CLEANUP $end
$var parameter 3 - s_IDLE $end
$var parameter 3 . s_RX_DATA_BITS $end
$var parameter 3 / s_RX_START_BIT $end
$var parameter 3 0 s_RX_STOP_BIT $end
$var reg 3 1 r_Bit_Index [2:0] $end
$var reg 8 2 r_Clock_Count [7:0] $end
$var reg 8 3 r_Rx_Byte [7:0] $end
$var reg 1 4 r_Rx_DV $end
$var reg 1 5 r_Rx_Data $end
$var reg 1 6 r_Rx_Data_R $end
$var reg 3 7 r_SM_Main [2:0] $end
$upscope $end
$scope module UUT $end
$var wire 1 ' i_Clock $end
$var wire 1 ( i_Rx_Serial $end
$var wire 1 8 w_Tx_Done $end
$var wire 1 9 w_Tx_Active $end
$var wire 1 : w_Rx_DV $end
$var wire 8 ; w_Rx_Byte [7:0] $end
$var wire 1 ! o_Tx_Serial $end
$var parameter 32 < CLKS_PER_BIT $end
$scope module UART_RX_INST $end
$var wire 1 ' i_Clock $end
$var wire 1 ( i_Rx_Serial $end
$var wire 8 = o_Rx_Byte [7:0] $end
$var wire 1 : o_Rx_DV $end
$var parameter 32 > CLKS_PER_BIT $end
$var parameter 3 ? s_CLEANUP $end
$var parameter 3 @ s_IDLE $end
$var parameter 3 A s_RX_DATA_BITS $end
$var parameter 3 B s_RX_START_BIT $end
$var parameter 3 C s_RX_STOP_BIT $end
$var reg 3 D r_Bit_Index [2:0] $end
$var reg 8 E r_Clock_Count [7:0] $end
$var reg 8 F r_Rx_Byte [7:0] $end
$var reg 1 G r_Rx_DV $end
$var reg 1 H r_Rx_Data $end
$var reg 1 I r_Rx_Data_R $end
$var reg 3 J r_SM_Main [2:0] $end
$upscope $end
$scope module UART_TX_INST $end
$var wire 1 ' i_Clock $end
$var wire 8 K i_Tx_Byte [7:0] $end
$var wire 1 : i_Tx_DV $end
$var wire 1 9 o_Tx_Active $end
$var wire 1 8 o_Tx_Done $end
$var parameter 32 L CLKS_PER_BIT $end
$var parameter 3 M s_CLEANUP $end
$var parameter 3 N s_IDLE $end
$var parameter 3 O s_TX_DATA_BITS $end
$var parameter 3 P s_TX_START_BIT $end
$var parameter 3 Q s_TX_STOP_BIT $end
$var reg 1 ! o_Tx_Serial $end
$var reg 3 R r_Bit_Index [2:0] $end
$var reg 8 S r_Clock_Count [7:0] $end
$var reg 3 T r_SM_Main [2:0] $end
$var reg 1 U r_Tx_Active $end
$var reg 8 V r_Tx_Data [7:0] $end
$var reg 1 W r_Tx_Done $end
$upscope $end
$upscope $end
$scope task UART_WRITE_BYTE $end
$var reg 8 X i_Data [7:0] $end
$var integer 32 Y ii [31:0] $end
$upscope $end
$upscope $end
$enddefinitions $end
$comment Show the parameter values. $end
$dumpall
b11 Q
b1 P
b10 O
b0 N
b100 M
b11101010 L
b11 C
b1 B
b10 A
b0 @
b100 ?
b11101010 >
b11101010 <
b11 0
b1 /
b10 .
b0 -
b100 ,
b11101010 +
b100101 &
b11101010 %
b10000111010010 $
$end
#0
$dumpvars
bx Y
bx X
0W
b0 V
0U
b0 T
b0 S
b0 R
b0 K
b0 J
1I
1H
0G
b0 F
b0 E
b0 D
b0 =
b0 ;
0:
09
08
b0 7
16
15
04
b0 3
b0 2
b0 1
b0 *
bx )
1(
0'
b0 #
0"
x!
$end
#1800
1!
x6
b11111111 )
1'
#3600
0'
#5400
0(
x5
16
b11111111 X
1'
#7200
0'
#9000
0I
15
1'
#10800
0'
#12600
0H
1'
#14400
0'
#16200
b1 J
1'
#18000
0'
#19800
b1 E
1'
#21600
0'
#23400
b10 E
1'
#25200
0'
#27000
b11 E
1'
#28800
0'
#30600
b100 E
1'
#32400
0'
#34200
b101 E
1'
#36000
0'
#37800
b110 E
1'
#39600
0'
#41400
b111 E
1'
#43200
0'
#45000
b1000 E
1'
#46800
0'
#48600
b1001 E
1'
#50400
0'
#52200
b1010 E
1'
#54000
0'
#55800
b1011 E
1'
#57600
0'
#59400
b1100 E
1'
#61200
0'
#63000
b1101 E
1'
#64800
0'
#66600
b1110 E
1'
#68400
0'
#70200
b1111 E
1'
#72000
0'
#73800
b10000 E
1'
#75600
0'
#77400
b10001 E
1'
#79200
0'
#81000
b10010 E
1'
#82800
0'
#84600
b10011 E
1'
#86400
0'
#88200
b10100 E
1'
#90000
0'
#91800
b10101 E
1'
#93600
0'
#95400
b10110 E
1'
#97200
0'
#99000
b10111 E
1'
#100800
0'
#102600
b11000 E
1'
#104400
0'
#106200
b11001 E
1'
#108000
0'
#109800
b11010 E
1'
#111600
0'
#113400
b11011 E
1'
#115200
0'
#117000
b11100 E
1'
#118800
0'
#120600
b11101 E
1'
#122400
0'
#124200
b11110 E
1'
#126000
0'
#127800
b11111 E
1'
#129600
0'
#131400
b100000 E
1'
#133200
0'
#135000
b100001 E
1'
#136800
0'
#138600
b100010 E
1'
#140400
0'
#142200
b100011 E
1'
#144000
0'
#145800
b100100 E
1'
#147600
0'
#149400
b100101 E
1'
#151200
0'
#153000
b100110 E
1'
#154800
0'
#156600
b100111 E
1'
#158400
0'
#160200
b101000 E
1'
#162000
0'
#163800
b101001 E
1'
#165600
0'
#167400
b101010 E
1'
#169200
0'
#171000
b101011 E
1'
#172800
0'
#174600
b101100 E
1'
#176400
0'
#178200
b101101 E
1'
#180000
0'
#181800
b101110 E
1'
#183600
0'
#185400
b101111 E
1'
#187200
0'
#189000
b110000 E
1'
#190800
0'
#192600
b110001 E
1'
#194400
0'
#196200
b110010 E
1'
#198000
0'
#199800
b110011 E
1'
#201600
0'
#203400
b110100 E
1'
#205200
0'
#207000
b110101 E
1'
#208800
0'
#210600
b110110 E
1'
#212400
0'
#214200
b110111 E
1'
#216000
0'
#217800
b111000 E
1'
#219600
0'
#221400
b111001 E
1'
#223200
0'
#225000
b111010 E
1'
#226800
0'
#228600
b111011 E
1'
#230400
0'
#232200
b111100 E
1'
#234000
0'
#235800
b111101 E
1'
#237600
0'
#239400
b111110 E
1'
#241200
0'
#243000
b111111 E
1'
#244800
0'
#246600
b1000000 E
1'
#248400
0'
#250200
b1000001 E
1'
#252000
0'
#253800
b1000010 E
1'
#255600
0'
#257400
b1000011 E
1'
#259200
0'
#261000
b1000100 E
1'
#262800
0'
#264600
b1000101 E
1'
#266400
0'
#268200
b1000110 E
1'
#270000
0'
#271800
b1000111 E
1'
#273600
0'
#275400
b1001000 E
1'
#277200
0'
#279000
b1001001 E
1'
#280800
0'
#282600
b1001010 E
1'
#284400
0'
#286200
b1001011 E
1'
#288000
0'
#289800
b1001100 E
1'
#291600
0'
#293400
b1001101 E
1'
#295200
0'
#297000
b1001110 E
1'
#298800
0'
#300600
b1001111 E
1'
#302400
0'
#304200
b1010000 E
1'
#306000
0'
#307800
b1010001 E
1'
#309600
0'
#311400
b1010010 E
1'
#313200
0'
#315000
b1010011 E
1'
#316800
0'
#318600
b1010100 E
1'
#320400
0'
#322200
b1010101 E
1'
#324000
0'
#325800
b1010110 E
1'
#327600
0'
#329400
b1010111 E
1'
#331200
0'
#333000
b1011000 E
1'
#334800
0'
#336600
b1011001 E
1'
#338400
0'
#340200
b1011010 E
1'
#342000
0'
#343800
b1011011 E
1'
#345600
0'
#347400
b1011100 E
1'
#349200
0'
#351000
b1011101 E
1'
#352800
0'
#354600
b1011110 E
1'
#356400
0'
#358200
b1011111 E
1'
#360000
0'
#361800
b1100000 E
1'
#363600
0'
#365400
b1100001 E
1'
#367200
0'
#369000
b1100010 E
1'
#370800
0'
#372600
b1100011 E
1'
#374400
0'
#376200
b1100100 E
1'
#378000
0'
#379800
b1100101 E
1'
#381600
0'
#383400
b1100110 E
1'
#385200
0'
#387000
b1100111 E
1'
#388800
0'
#390600
b1101000 E
1'
#392400
0'
#394200
b1101001 E
1'
#396000
0'
#397800
b1101010 E
1'
#399600
0'
#401400
b1101011 E
1'
#403200
0'
#405000
b1101100 E
1'
#406800
0'
#408600
b1101101 E
1'
#410400
0'
#412200
b1101110 E
1'
#414000
0'
#415800
b1101111 E
1'
#417600
0'
#419400
b1110000 E
1'
#421200
0'
#423000
b1110001 E
1'
#424800
0'
#426600
b1110010 E
1'
#428400
0'
#430200
b1110011 E
1'
#432000
0'
#433800
b1110100 E
1'
#435600
0'
#437400
b10 J
b0 E
1'
#439200
0'
#441000
b1 E
1'
#442800
0'
#444600
b10 E
1'
#446400
0'
#448200
b11 E
1'
#450000
0'
#451800
b100 E
1'
#453600
0'
#455400
b101 E
1'
#457200
0'
#459000
b110 E
1'
#460800
0'
#462600
b111 E
1'
#464400
0'
#466200
b1000 E
1'
#468000
0'
#469800
b1001 E
1'
#471600
0'
#473400
b1010 E
1'
#475200
0'
#477000
b1011 E
1'
#478800
0'
#480600
b1100 E
1'
#482400
0'
#484200
b1101 E
1'
#486000
0'
#487800
b1110 E
1'
#489600
0'
#491400
b1111 E
1'
#493200
0'
#495000
b10000 E
1'
#496800
0'
#498600
b10001 E
1'
#500400
0'
#502200
b10010 E
1'
#504000
0'
#505800
b10011 E
1'
#507600
0'
#509400
b10100 E
1'
#511200
0'
#513000
b10101 E
1'
#514800
0'
#516600
b10110 E
1'
#518400
0'
#520200
b10111 E
1'
#522000
0'
#523800
b11000 E
1'
#525600
0'
#527400
b11001 E
1'
#529200
0'
#531000
b11010 E
1'
#532800
0'
#534600
b11011 E
1'
#536400
0'
#538200
b11100 E
1'
#540000
0'
#541800
b11101 E
1'
#543600
0'
#545400
b11110 E
1'
#547200
0'
#549000
b11111 E
1'
#550800
0'
#552600
b100000 E
1'
#554400
0'
#556200
b100001 E
1'
#558000
0'
#559800
b100010 E
1'
#561600
0'
#563400
b100011 E
1'
#565200
0'
#567000
b100100 E
1'
#568800
0'
#570600
b100101 E
1'
#572400
0'
#574200
b100110 E
1'
#576000
0'
#577800
b100111 E
1'
#579600
0'
#581400
b101000 E
1'
#583200
0'
#585000
b101001 E
1'
#586800
0'
#588600
b101010 E
1'
#590400
0'
#592200
b101011 E
1'
#594000
0'
#595800
b101100 E
1'
#597600
0'
#599400
b101101 E
1'
#601200
0'
#603000
b101110 E
1'
#604800
0'
#606600
b101111 E
1'
#608400
0'
#610200
b110000 E
1'
#612000
0'
#613800
b110001 E
1'
#615600
0'
#617400
b110010 E
1'
#619200
0'
#621000
b110011 E
1'
#622800
0'
#624600
b110100 E
1'
#626400
0'
#628200
b110101 E
1'
#630000
0'
#631800
b110110 E
1'
#633600
0'
#635400
b110111 E
1'
#637200
0'
#639000
b111000 E
1'
#640800
0'
#642600
b111001 E
1'
#644400
0'
#646200
b111010 E
1'
#648000
0'
#649800
b111011 E
1'
#651600
0'
#653400
b111100 E
1'
#655200
0'
#657000
b111101 E
1'
#658800
0'
#660600
b111110 E
1'
#662400
0'
#664200
b111111 E
1'
#666000
0'
#667800
b1000000 E
1'
#669600
0'
#671400
b1000001 E
1'
#673200
0'
#675000
b1000010 E
1'
#676800
0'
#678600
b1000011 E
1'
#680400
0'
#682200
b1000100 E
1'
#684000
0'
#685800
b1000101 E
1'
#687600
0'
#689400
b1000110 E
1'
#691200
0'
#693000
b1000111 E
1'
#694800
0'
#696600
b1001000 E
1'
#698400
0'
#700200
b1001001 E
1'
#702000
0'
#703800
b1001010 E
1'
#705600
0'
#707400
b1001011 E
1'
#709200
0'
#711000
b1001100 E
1'
#712800
0'
#714600
b1001101 E
1'
#716400
0'
#718200
b1001110 E
1'
#720000
0'
#721800
b1001111 E
1'
#723600
0'
#725400
b1010000 E
1'
#727200
0'
#729000
b1010001 E
1'
#730800
0'
#732600
b1010010 E
1'
#734400
0'
#736200
b1010011 E
1'
#738000
0'
#739800
b1010100 E
1'
#741600
0'
#743400
b1010101 E
1'
#745200
0'
#747000
b1010110 E
1'
#748800
0'
#750600
b1010111 E
1'
#752400
0'
#754200
b1011000 E
1'
#756000
0'
#757800
b1011001 E
1'
#759600
0'
#761400
b1011010 E
1'
#763200
0'
#765000
b1011011 E
1'
#766800
0'
#768600
b1011100 E
1'
#770400
0'
#772200
b1011101 E
1'
#774000
0'
#775800
b1011110 E
1'
#777600
0'
#779400
b1011111 E
1'
#781200
0'
#783000
b1100000 E
1'
#784800
0'
#786600
b1100001 E
1'
#788400
0'
#790200
b1100010 E
1'
#792000
0'
#793800
b1100011 E
1'
#795600
0'
#797400
b1100100 E
1'
#799200
0'
#801000
b1100101 E
1'
#802800
0'
#804600
b1100110 E
1'
#806400
0'
#808200
b1100111 E
1'
#810000
0'
#811800
b1101000 E
1'
#813600
0'
#815400
b1101001 E
1'
#817200
0'
#819000
b1101010 E
1'
#820800
0'
#822600
b1101011 E
1'
#824400
0'
#826200
b1101100 E
1'
#828000
0'
#829800
b1101101 E
1'
#831600
0'
#833400
b1101110 E
1'
#835200
0'
#837000
b1101111 E
1'
#838800
0'
#840600
b1110000 E
1'
#842400
0'
#844200
b1110001 E
1'
#846000
0'
#847800
b1110010 E
1'
#849600
0'
#851400
b1110011 E
1'
#853200
0'
#855000
b1110100 E
1'
#856800
0'
#858600
b1110101 E
1'
#860400
0'
#862200
b1110110 E
1'
#864000
0'
#865800
b1110111 E
1'
#867600
0'
#869400
b1111000 E
1'
#871200
0'
1(
b0 Y
#873000
1I
b1111001 E
1'
#874800
0'
#876600
b1111010 E
1H
1'
#878400
0'
#880200
b1111011 E
1'
#882000
0'
#883800
b1111100 E
1'
#885600
0'
#887400
b1111101 E
1'
#889200
0'
#891000
b1111110 E
1'
#892800
0'
#894600
b1111111 E
1'
#896400
0'
#898200
b10000000 E
1'
#900000
0'
#901800
b10000001 E
1'
#903600
0'
#905400
b10000010 E
1'
#907200
0'
#909000
b10000011 E
1'
#910800
0'
#912600
b10000100 E
1'
#914400
0'
#916200
b10000101 E
1'
#918000
0'
#919800
b10000110 E
1'
#921600
0'
#923400
b10000111 E
1'
#925200
0'
#927000
b10001000 E
1'
#928800
0'
#930600
b10001001 E
1'
#932400
0'
#934200
b10001010 E
1'
#936000
0'
#937800
b10001011 E
1'
#939600
0'
#941400
b10001100 E
1'
#943200
0'
#945000
b10001101 E
1'
#946800
0'
#948600
b10001110 E
1'
#950400
0'
#952200
b10001111 E
1'
#954000
0'
#955800
b10010000 E
1'
#957600
0'
#959400
b10010001 E
1'
#961200
0'
#963000
b10010010 E
1'
#964800
0'
#966600
b10010011 E
1'
#968400
0'
#970200
b10010100 E
1'
#972000
0'
#973800
b10010101 E
1'
#975600
0'
#977400
b10010110 E
1'
#979200
0'
#981000
b10010111 E
1'
#982800
0'
#984600
b10011000 E
1'
#986400
0'
#988200
b10011001 E
1'
#990000
0'
#991800
b10011010 E
1'
#993600
0'
#995400
b10011011 E
1'
#997200
0'
#999000
b10011100 E
1'
#1000800
0'
#1002600
b10011101 E
1'
#1004400
0'
#1006200
b10011110 E
1'
#1008000
0'
#1009800
b10011111 E
1'
#1011600
0'
#1013400
b10100000 E
1'
#1015200
0'
#1017000
b10100001 E
1'
#1018800
0'
#1020600
b10100010 E
1'
#1022400
0'
#1024200
b10100011 E
1'
#1026000
0'
#1027800
b10100100 E
1'
#1029600
0'
#1031400
b10100101 E
1'
#1033200
0'
#1035000
b10100110 E
1'
#1036800
0'
#1038600
b10100111 E
1'
#1040400
0'
#1042200
b10101000 E
1'
#1044000
0'
#1045800
b10101001 E
1'
#1047600
0'
#1049400
b10101010 E
1'
#1051200
0'
#1053000
b10101011 E
1'
#1054800
0'
#1056600
b10101100 E
1'
#1058400
0'
#1060200
b10101101 E
1'
#1062000
0'
#1063800
b10101110 E
1'
#1065600
0'
#1067400
b10101111 E
1'
#1069200
0'
#1071000
b10110000 E
1'
#1072800
0'
#1074600
b10110001 E
1'
#1076400
0'
#1078200
b10110010 E
1'
#1080000
0'
#1081800
b10110011 E
1'
#1083600
0'
#1085400
b10110100 E
1'
#1087200
0'
#1089000
b10110101 E
1'
#1090800
0'
#1092600
b10110110 E
1'
#1094400
0'
#1096200
b10110111 E
1'
#1098000
0'
#1099800
b10111000 E
1'
#1101600
0'
#1103400
b10111001 E
1'
#1105200
0'
#1107000
b10111010 E
1'
#1108800
0'
#1110600
b10111011 E
1'
#1112400
0'
#1114200
b10111100 E
1'
#1116000
0'
#1117800
b10111101 E
1'
#1119600
0'
#1121400
b10111110 E
1'
#1123200
0'
#1125000
b10111111 E
1'
#1126800
0'
#1128600
b11000000 E
1'
#1130400
0'
#1132200
b11000001 E
1'
#1134000
0'
#1135800
b11000010 E
1'
#1137600
0'
#1139400
b11000011 E
1'
#1141200
0'
#1143000
b11000100 E
1'
#1144800
0'
#1146600
b11000101 E
1'
#1148400
0'
#1150200
b11000110 E
1'
#1152000
0'
#1153800
b11000111 E
1'
#1155600
0'
#1157400
b11001000 E
1'
#1159200
0'
#1161000
b11001001 E
1'
#1162800
0'
#1164600
b11001010 E
1'
#1166400
0'
#1168200
b11001011 E
1'
#1170000
0'
#1171800
b11001100 E
1'
#1173600
0'
#1175400
b11001101 E
1'
#1177200
0'
#1179000
b11001110 E
1'
#1180800
0'
#1182600
b11001111 E
1'
#1184400
0'
#1186200
b11010000 E
1'
#1188000
0'
#1189800
b11010001 E
1'
#1191600
0'
#1193400
b11010010 E
1'
#1195200
0'
#1197000
b11010011 E
1'
#1198800
0'
#1200600
b11010100 E
1'
#1202400
0'
#1204200
b11010101 E
1'
#1206000
0'
#1207800
b11010110 E
1'
#1209600
0'
#1211400
b11010111 E
1'
#1213200
0'
#1215000
b11011000 E
1'
#1216800
0'
#1218600
b11011001 E
1'
#1220400
0'
#1222200
b11011010 E
1'
#1224000
0'
#1225800
b11011011 E
1'
#1227600
0'
#1229400
b11011100 E
1'
#1231200
0'
#1233000
b11011101 E
1'
#1234800
0'
#1236600
b11011110 E
1'
#1238400
0'
#1240200
b11011111 E
1'
#1242000
0'
#1243800
b11100000 E
1'
#1245600
0'
#1247400
b11100001 E
1'
#1249200
0'
#1251000
b11100010 E
1'
#1252800
0'
#1254600
b11100011 E
1'
#1256400
0'
#1258200
b11100100 E
1'
#1260000
0'
#1261800
b11100101 E
1'
#1263600
0'
#1265400
b11100110 E
1'
#1267200
0'
#1269000
b11100111 E
1'
#1270800
0'
#1272600
b11101000 E
1'
#1274400
0'
#1276200
b11101001 E
1'
#1278000
0'
#1279800
b1 D
b1 ;
b1 =
b1 K
b1 F
b0 E
1'
#1281600
0'
#1283400
b1 E
1'
#1285200
0'
#1287000
b10 E
1'
#1288800
0'
#1290600
b11 E
1'
#1292400
0'
#1294200
b100 E
1'
#1296000
0'
#1297800
b101 E
1'
#1299600
0'
#1301400
b110 E
1'
#1303200
0'
#1305000
b111 E
1'
#1306800
0'
#1308600
b1000 E
1'
#1310400
0'
#1312200
b1001 E
1'
#1314000
0'
#1315800
b1010 E
1'
#1317600
0'
#1319400
b1011 E
1'
#1321200
0'
#1323000
b1100 E
1'
#1324800
0'
#1326600
b1101 E
1'
#1328400
0'
#1330200
b1110 E
1'
#1332000
0'
#1333800
b1111 E
1'
#1335600
0'
#1337400
b10000 E
1'
#1339200
0'
#1341000
b10001 E
1'
#1342800
0'
#1344600
b10010 E
1'
#1346400
0'
#1348200
b10011 E
1'
#1350000
0'
#1351800
b10100 E
1'
#1353600
0'
#1355400
b10101 E
1'
#1357200
0'
#1359000
b10110 E
1'
#1360800
0'
#1362600
b10111 E
1'
#1364400
0'
#1366200
b11000 E
1'
